[{"inventory_num": 3808, "inventory_id": "NL-HaNA_1.01.02_3808", "session_date": "1753-01-03", "date": "1753-01-03", "date_line": "NL-HaNA_1.01.02_3808_0066-line-515-1901-662-68", "date_scan": "NL-HaNA_1.01.02_3808_0066", "date_string": "Mercurii den 3 January"}, {"inventory_num": 3808, "inventory_id": "NL-HaNA_1.01.02_3808", "session_date": "1753-01-04", "date": "1753-01-04", "date_line": "NL-HaNA_1.01.02_3808_0067-line-2538-2621-571-60", "date_scan": "NL-HaNA_1.01.02_3808_0067", "date_string": "Jovis den 4 January"}, {"inventory_num": 3808, "inventory_id": "NL-HaNA_1.01.02_3808", "session_date": "1753-01-05", "date": "1753-01-05", "date_line": "NL-HaNA_1.01.02_3808_0068-line-2555-1680-621-58", "date_scan": "NL-HaNA_1.01.02_3808_0068", "date_string": "Veneris den 5 January"}, {"inventory_num": 3808, "inventory_id": "NL-HaNA_1.01.02_3808", "session_date": "1753-01-06", "date": "1753-01-06", "date_line": "NL-HaNA_1.01.02_3808_0069-line-523-2003-625-67", "date_scan": "NL-HaNA_1.01.02_3808_0069", "date_string": "Sabbathi den 6 January"}, {"inventory_num": 3808, "inventory_id": "NL-HaNA_1.01.02_3808", "session_date": "1753-01-08", "date": "1753-01-07", "date_line": "NL-HaNA_1.01.02_3808_0069-line-2524-3069-657-67", "date_scan": "NL-HaNA_1.01.02_3808_0069", "date_string": "Dominica den 7 January"}, {"inventory_num": 3808, "inventory_id": "NL-HaNA_1.01.02_3808", "session_date": "1753-01-08", "date": "1753-01-08", "date_line": "NL-HaNA_1.01.02_3808_0069-line-2554-3232-572-66", "date_scan": "NL-HaNA_1.01.02_3808_0069", "date_string": "Luna den 8 January"}, {"inventory_num": 3808, "inventory_id": "NL-HaNA_1.01.02_3808", "session_date": "1753-01-09", "date": "1753-01-09", "date_line": "NL-HaNA_1.01.02_3808_0071-line-514-354-583-58", "date_scan": "NL-HaNA_1.01.02_3808_0071", "date_string": "Martis den 9 January"}, {"inventory_num": 3808, "inventory_id": "NL-HaNA_1.01.02_3808", "session_date": "1753-01-10", "date": "1753-01-10", "date_line": "NL-HaNA_1.01.02_3808_0071-line-2497-1725-676-57", "date_scan": "NL-HaNA_1.01.02_3808_0071", "date_string": "Mercurii den 10 January"}, {"inventory_num": 3808, "inventory_id": "NL-HaNA_1.01.02_3808", "session_date": "1753-01-11", "date": "1753-01-11", "date_line": "NL-HaNA_1.01.02_3808_0073-line-1476-2828-589-62", "date_scan": "NL-HaNA_1.01.02_3808_0073", "date_string": "Jovis den 11 January"}, {"inventory_num": 3808, "inventory_id": "NL-HaNA_1.01.02_3808", "session_date": "1753-01-12", "date": "1753-01-12", "date_line": "NL-HaNA_1.01.02_3808_0073-line-2539-1325-627-60", "date_scan": "NL-HaNA_1.01.02_3808_0073", "date_string": "Veneris den 12 January"}, {"inventory_num": 3808, "inventory_id": "NL-HaNA_1.01.02_3808", "session_date": "1753-01-13", "date": "1753-01-13", "date_line": "NL-HaNA_1.01.02_3808_0075-line-1479-1204-655-64", "date_scan": "NL-HaNA_1.01.02_3808_0075", "date_string": "Sabbathi den 13 January"}, {"inventory_num": 3808, "inventory_id": "NL-HaNA_1.01.02_3808", "session_date": "1753-01-15", "date": "1753-01-14", "date_line": "NL-HaNA_1.01.02_3808_0076-line-1418-1733-689-58", "date_scan": "NL-HaNA_1.01.02_3808_0076", "date_string": "Dominica den 14 January"}, {"inventory_num": 3808, "inventory_id": "NL-HaNA_1.01.02_3808", "session_date": "1753-01-15", "date": "1753-01-15", "date_line": "NL-HaNA_1.01.02_3808_0076-line-1462-1891-591-74", "date_scan": "NL-HaNA_1.01.02_3808_0076", "date_string": "Luna den 15 January"}, {"inventory_num": 3808, "inventory_id": "NL-HaNA_1.01.02_3808", "session_date": "1753-01-16", "date": "1753-01-16", "date_line": "NL-HaNA_1.01.02_3808_0077-line-1470-2531-616-68", "date_scan": "NL-HaNA_1.01.02_3808_0077", "date_string": "Martis den 16 January"}, {"inventory_num": 3808, "inventory_id": "NL-HaNA_1.01.02_3808", "session_date": "1753-01-17", "date": "1753-01-17", "date_line": "NL-HaNA_1.01.02_3808_0078-line-503-800-682-57", "date_scan": "NL-HaNA_1.01.02_3808_0078", "date_string": "Mercurii den 17 January"}, {"inventory_num": 3808, "inventory_id": "NL-HaNA_1.01.02_3808", "session_date": "1753-01-18", "date": "1753-01-18", "date_line": "NL-HaNA_1.01.02_3808_0079-line-3508-798-588-66", "date_scan": "NL-HaNA_1.01.02_3808_0079", "date_string": "Jovis den 18 January"}, {"inventory_num": 3808, "inventory_id": "NL-HaNA_1.01.02_3808", "session_date": "1753-01-19", "date": "1753-01-19", "date_line": "NL-HaNA_1.01.02_3808_0080-line-1483-2579-624-55", "date_scan": "NL-HaNA_1.01.02_3808_0080", "date_string": "Veneris den 19 January"}, {"inventory_num": 3808, "inventory_id": "NL-HaNA_1.01.02_3808", "session_date": "1753-01-20", "date": "1753-01-20", "date_line": "NL-HaNA_1.01.02_3808_0080-line-3482-2942-660-76", "date_scan": "NL-HaNA_1.01.02_3808_0080", "date_string": "Sabbathi den 20 January"}, {"inventory_num": 3808, "inventory_id": "NL-HaNA_1.01.02_3808", "session_date": "1753-01-22", "date": "1753-01-21", "date_line": "NL-HaNA_1.01.02_3808_0083-line-3437-2856-684-62", "date_scan": "NL-HaNA_1.01.02_3808_0083", "date_string": "Dominica den 21 January"}, {"inventory_num": 3808, "inventory_id": "NL-HaNA_1.01.02_3808", "session_date": "1753-01-22", "date": "1753-01-22", "date_line": "NL-HaNA_1.01.02_3808_0083-line-3485-3011-580-66", "date_scan": "NL-HaNA_1.01.02_3808_0083", "date_string": "Luna den 22 January"}, {"inventory_num": 3808, "inventory_id": "NL-HaNA_1.01.02_3808", "session_date": "1753-01-23", "date": "1753-01-23", "date_line": "NL-HaNA_1.01.02_3808_0085-line-3452-2094-618-69", "date_scan": "NL-HaNA_1.01.02_3808_0085", "date_string": "Martis den 23 January"}, {"inventory_num": 3808, "inventory_id": "NL-HaNA_1.01.02_3808", "session_date": "1753-01-24", "date": "1753-01-24", "date_line": "NL-HaNA_1.01.02_3808_0087-line-450-1594-690-59", "date_scan": "NL-HaNA_1.01.02_3808_0087", "date_string": "Mercurii den 24 January"}, {"inventory_num": 3808, "inventory_id": "NL-HaNA_1.01.02_3808", "session_date": "1753-01-25", "date": "1753-01-25", "date_line": "NL-HaNA_1.01.02_3808_0087-line-2542-796-588-70", "date_scan": "NL-HaNA_1.01.02_3808_0087", "date_string": "Jovis den 25 January"}, {"inventory_num": 3808, "inventory_id": "NL-HaNA_1.01.02_3808", "session_date": "1753-01-26", "date": "1753-01-26", "date_line": "NL-HaNA_1.01.02_3808_0087-line-2489-2803-625-58", "date_scan": "NL-HaNA_1.01.02_3808_0087", "date_string": "Veneris den 26 January"}, {"inventory_num": 3808, "inventory_id": "NL-HaNA_1.01.02_3808", "session_date": "1753-01-27", "date": "1753-01-27", "date_line": "NL-HaNA_1.01.02_3808_0089-line-1441-2374-658-61", "date_scan": "NL-HaNA_1.01.02_3808_0089", "date_string": "Sabbathi den 27 January"}, {"inventory_num": 3808, "inventory_id": "NL-HaNA_1.01.02_3808", "session_date": "1753-01-29", "date": "1753-01-28", "date_line": "NL-HaNA_1.01.02_3808_0089-line-2489-2587-685-59", "date_scan": "NL-HaNA_1.01.02_3808_0089", "date_string": "Dominica den 28 January"}, {"inventory_num": 3808, "inventory_id": "NL-HaNA_1.01.02_3808", "session_date": "1753-01-29", "date": "1753-01-29", "date_line": "NL-HaNA_1.01.02_3808_0089-line-2534-2765-586-57", "date_scan": "NL-HaNA_1.01.02_3808_0089", "date_string": "Luna den 29 January"}, {"inventory_num": 3808, "inventory_id": "NL-HaNA_1.01.02_3808", "session_date": "1753-01-30", "date": "1753-01-30", "date_line": "NL-HaNA_1.01.02_3808_0091-line-1507-1740-625-60", "date_scan": "NL-HaNA_1.01.02_3808_0091", "date_string": "Martis den 30 January"}, {"inventory_num": 3808, "inventory_id": "NL-HaNA_1.01.02_3808", "session_date": "1753-01-31", "date": "1753-01-31", "date_line": "NL-HaNA_1.01.02_3808_0091-line-2520-2495-674-65", "date_scan": "NL-HaNA_1.01.02_3808_0091", "date_string": "Mercurii den 31 January"}, {"inventory_num": 3808, "inventory_id": "NL-HaNA_1.01.02_3808", "session_date": "1753-02-01", "date": "1753-02-01", "date_line": "NL-HaNA_1.01.02_3808_0092-line-537-2300-580-60", "date_scan": "NL-HaNA_1.01.02_3808_0092", "date_string": "Jovis den 1 February"}, {"inventory_num": 3808, "inventory_id": "NL-HaNA_1.01.02_3808", "session_date": "1753-02-02", "date": "1753-02-02", "date_line": "NL-HaNA_1.01.02_3808_0093-line-2545-540-621-58", "date_scan": "NL-HaNA_1.01.02_3808_0093", "date_string": "Veneris den 2 February"}, {"inventory_num": 3808, "inventory_id": "NL-HaNA_1.01.02_3808", "session_date": "1753-02-03", "date": "1753-02-03", "date_line": "NL-HaNA_1.01.02_3808_0094-line-483-1338-647-58", "date_scan": "NL-HaNA_1.01.02_3808_0094", "date_string": "Sabbathi den 3 February"}, {"inventory_num": 3808, "inventory_id": "NL-HaNA_1.01.02_3808", "session_date": "1753-02-05", "date": "1753-02-04", "date_line": "NL-HaNA_1.01.02_3808_0096-line-2458-3119-681-63", "date_scan": "NL-HaNA_1.01.02_3808_0096", "date_string": "Dominica den 4 February"}, {"inventory_num": 3808, "inventory_id": "NL-HaNA_1.01.02_3808", "session_date": "1753-02-05", "date": "1753-02-05", "date_line": "NL-HaNA_1.01.02_3808_0096-line-2507-3282-573-58", "date_scan": "NL-HaNA_1.01.02_3808_0096", "date_string": "Luna den 5 February"}, {"inventory_num": 3808, "inventory_id": "NL-HaNA_1.01.02_3808", "session_date": "1753-02-06", "date": "1753-02-06", "date_line": "NL-HaNA_1.01.02_3808_0097-line-3501-2581-608-61", "date_scan": "NL-HaNA_1.01.02_3808_0097", "date_string": "Martis den 6 February"}, {"inventory_num": 3808, "inventory_id": "NL-HaNA_1.01.02_3808", "session_date": "1753-02-07", "date": "1753-02-07", "date_line": "NL-HaNA_1.01.02_3808_0099-line-484-1726-680-73", "date_scan": "NL-HaNA_1.01.02_3808_0099", "date_string": "Mercurii den 7 February"}, {"inventory_num": 3808, "inventory_id": "NL-HaNA_1.01.02_3808", "session_date": "1753-02-08", "date": "1753-02-08", "date_line": "NL-HaNA_1.01.02_3808_0102-line-485-1903-575-58", "date_scan": "NL-HaNA_1.01.02_3808_0102", "date_string": "Jovis den 8 February"}, {"inventory_num": 3808, "inventory_id": "NL-HaNA_1.01.02_3808", "session_date": "1753-02-09", "date": "1753-02-09", "date_line": "NL-HaNA_1.01.02_3808_0103-line-3483-659-619-65", "date_scan": "NL-HaNA_1.01.02_3808_0103", "date_string": "Veneris den 9 February"}, {"inventory_num": 3808, "inventory_id": "NL-HaNA_1.01.02_3808", "session_date": "1753-02-10", "date": "1753-02-10", "date_line": "NL-HaNA_1.01.02_3808_0104-line-1407-1296-670-69", "date_scan": "NL-HaNA_1.01.02_3808_0104", "date_string": "Sabbathi den 10 February"}, {"inventory_num": 3808, "inventory_id": "NL-HaNA_1.01.02_3808", "session_date": "1753-02-12", "date": "1753-02-11", "date_line": "NL-HaNA_1.01.02_3808_0105-line-420-3146-706-69", "date_scan": "NL-HaNA_1.01.02_3808_0105", "date_string": "Dominica den 11 February"}, {"inventory_num": 3808, "inventory_id": "NL-HaNA_1.01.02_3808", "session_date": "1753-02-12", "date": "1753-02-12", "date_line": "NL-HaNA_1.01.02_3808_0105-line-1441-408-608-67", "date_scan": "NL-HaNA_1.01.02_3808_0105", "date_string": "Luna den 12 February"}, {"inventory_num": 3808, "inventory_id": "NL-HaNA_1.01.02_3808", "session_date": "1753-02-13", "date": "1753-02-13", "date_line": "NL-HaNA_1.01.02_3808_0105-line-2481-2600-639-62", "date_scan": "NL-HaNA_1.01.02_3808_0105", "date_string": "Martis den 13 February"}, {"inventory_num": 3808, "inventory_id": "NL-HaNA_1.01.02_3808", "session_date": "1753-02-14", "date": "1753-02-14", "date_line": "NL-HaNA_1.01.02_3808_0106-line-2493-2418-708-72", "date_scan": "NL-HaNA_1.01.02_3808_0106", "date_string": "Mercurii den 14 February"}, {"inventory_num": 3808, "inventory_id": "NL-HaNA_1.01.02_3808", "session_date": "1753-02-15", "date": "1753-02-15", "date_line": "NL-HaNA_1.01.02_3808_0107-line-1452-1898-602-58", "date_scan": "NL-HaNA_1.01.02_3808_0107", "date_string": "Jovis den 15 February"}, {"inventory_num": 3808, "inventory_id": "NL-HaNA_1.01.02_3808", "session_date": "1753-02-16", "date": "1753-02-16", "date_line": "NL-HaNA_1.01.02_3808_0109-line-3536-2377-651-58", "date_scan": "NL-HaNA_1.01.02_3808_0109", "date_string": "Veneris den 16 February"}, {"inventory_num": 3808, "inventory_id": "NL-HaNA_1.01.02_3808", "session_date": "1753-02-17", "date": "1753-02-17", "date_line": "NL-HaNA_1.01.02_3808_0110-line-3462-1174-672-82", "date_scan": "NL-HaNA_1.01.02_3808_0110", "date_string": "Sabbathi den 17 February"}, {"inventory_num": 3808, "inventory_id": "NL-HaNA_1.01.02_3808", "session_date": "1753-02-19", "date": "1753-02-18", "date_line": "NL-HaNA_1.01.02_3808_0111-line-1432-829-706-66", "date_scan": "NL-HaNA_1.01.02_3808_0111", "date_string": "Dominica den 18 February"}, {"inventory_num": 3808, "inventory_id": "NL-HaNA_1.01.02_3808", "session_date": "1753-02-19", "date": "1753-02-19", "date_line": "NL-HaNA_1.01.02_3808_0111-line-1475-1021-602-61", "date_scan": "NL-HaNA_1.01.02_3808_0111", "date_string": "Luna den 19 February"}, {"inventory_num": 3808, "inventory_id": "NL-HaNA_1.01.02_3808", "session_date": "1753-02-20", "date": "1753-02-20", "date_line": "NL-HaNA_1.01.02_3808_0112-line-1442-884-642-61", "date_scan": "NL-HaNA_1.01.02_3808_0112", "date_string": "Martis den 20 February"}, {"inventory_num": 3808, "inventory_id": "NL-HaNA_1.01.02_3808", "session_date": "1753-02-21", "date": "1753-02-21", "date_line": "NL-HaNA_1.01.02_3808_0113-line-3418-3071-701-73", "date_scan": "NL-HaNA_1.01.02_3808_0113", "date_string": "Mercurii den 21 February"}, {"inventory_num": 3808, "inventory_id": "NL-HaNA_1.01.02_3808", "session_date": "1753-02-22", "date": "1753-02-22", "date_line": "NL-HaNA_1.01.02_3808_0115-line-507-2711-604-59", "date_scan": "NL-HaNA_1.01.02_3808_0115", "date_string": "Jovis den 22 February"}, {"inventory_num": 3808, "inventory_id": "NL-HaNA_1.01.02_3808", "session_date": "1753-02-23", "date": "1753-02-23", "date_line": "NL-HaNA_1.01.02_3808_0117-line-522-2237-647-54", "date_scan": "NL-HaNA_1.01.02_3808_0117", "date_string": "Veneris den 23 February"}, {"inventory_num": 3808, "inventory_id": "NL-HaNA_1.01.02_3808", "session_date": "1753-02-24", "date": "1753-02-24", "date_line": "NL-HaNA_1.01.02_3808_0117-line-3501-2995-670-61", "date_scan": "NL-HaNA_1.01.02_3808_0117", "date_string": "Sabbathi den 24 February"}, {"inventory_num": 3808, "inventory_id": "NL-HaNA_1.01.02_3808", "session_date": "1753-02-26", "date": "1753-02-25", "date_line": "NL-HaNA_1.01.02_3808_0118-line-1365-2753-708-67", "date_scan": "NL-HaNA_1.01.02_3808_0118", "date_string": "Dominica den 25 February"}, {"inventory_num": 3808, "inventory_id": "NL-HaNA_1.01.02_3808", "session_date": "1753-02-26", "date": "1753-02-26", "date_line": "NL-HaNA_1.01.02_3808_0118-line-1404-2948-608-65", "date_scan": "NL-HaNA_1.01.02_3808_0118", "date_string": "Luna den 26 February"}, {"inventory_num": 3808, "inventory_id": "NL-HaNA_1.01.02_3808", "session_date": "1753-02-27", "date": "1753-02-27", "date_line": "NL-HaNA_1.01.02_3808_0119-line-2515-2513-639-77", "date_scan": "NL-HaNA_1.01.02_3808_0119", "date_string": "Martis den 27 February"}, {"inventory_num": 3808, "inventory_id": "NL-HaNA_1.01.02_3808", "session_date": "1753-02-28", "date": "1753-02-28", "date_line": "NL-HaNA_1.01.02_3808_0120-line-2518-589-711-62", "date_scan": "NL-HaNA_1.01.02_3808_0120", "date_string": "Mercurii den 28 February"}, {"inventory_num": 3808, "inventory_id": "NL-HaNA_1.01.02_3808", "session_date": "1753-03-01", "date": "1753-03-01", "date_line": "NL-HaNA_1.01.02_3808_0121-line-558-1052-525-57", "date_scan": "NL-HaNA_1.01.02_3808_0121", "date_string": "Jovis den 1 Maart"}, {"inventory_num": 3808, "inventory_id": "NL-HaNA_1.01.02_3808", "session_date": "1753-03-02", "date": "1753-03-02", "date_line": "NL-HaNA_1.01.02_3808_0122-line-514-1708-554-50", "date_scan": "NL-HaNA_1.01.02_3808_0122", "date_string": "Veneris den 2 Maart"}, {"inventory_num": 3808, "inventory_id": "NL-HaNA_1.01.02_3808", "session_date": "1753-03-03", "date": "1753-03-03", "date_line": "NL-HaNA_1.01.02_3808_0122-line-2567-804-580-58", "date_scan": "NL-HaNA_1.01.02_3808_0122", "date_string": "Sabbathi den 3 Maart"}, {"inventory_num": 3808, "inventory_id": "NL-HaNA_1.01.02_3808", "session_date": "1753-03-05", "date": "1753-03-04", "date_line": "NL-HaNA_1.01.02_3808_0125-line-515-2104-623-58", "date_scan": "NL-HaNA_1.01.02_3808_0125", "date_string": "Dominica den 4 Maart"}, {"inventory_num": 3808, "inventory_id": "NL-HaNA_1.01.02_3808", "session_date": "1753-03-05", "date": "1753-03-05", "date_line": "NL-HaNA_1.01.02_3808_0125-line-555-2306-527-55", "date_scan": "NL-HaNA_1.01.02_3808_0125", "date_string": "Luna den 5 Maart"}, {"inventory_num": 3808, "inventory_id": "NL-HaNA_1.01.02_3808", "session_date": "1753-03-06", "date": "1753-03-06", "date_line": "NL-HaNA_1.01.02_3808_0127-line-552-1481-548-51", "date_scan": "NL-HaNA_1.01.02_3808_0127", "date_string": "Martis den 6 Maart"}, {"inventory_num": 3808, "inventory_id": "NL-HaNA_1.01.02_3808", "session_date": "1753-03-07", "date": "1753-03-07", "date_line": "NL-HaNA_1.01.02_3808_0129-line-526-1429-606-58", "date_scan": "NL-HaNA_1.01.02_3808_0129", "date_string": "Mercurii den 7 Maart"}, {"inventory_num": 3808, "inventory_id": "NL-HaNA_1.01.02_3808", "session_date": "1753-03-08", "date": "1753-03-08", "date_line": "NL-HaNA_1.01.02_3808_0129-line-2631-1527-508-67", "date_scan": "NL-HaNA_1.01.02_3808_0129", "date_string": "Jovis den 8 Maart"}, {"inventory_num": 3808, "inventory_id": "NL-HaNA_1.01.02_3808", "session_date": "1753-03-09", "date": "1753-03-09", "date_line": "NL-HaNA_1.01.02_3808_0130-line-2600-1057-561-55", "date_scan": "NL-HaNA_1.01.02_3808_0130", "date_string": "Veneris den 9 Maart"}, {"inventory_num": 3808, "inventory_id": "NL-HaNA_1.01.02_3808", "session_date": "1753-03-10", "date": "1753-03-10", "date_line": "NL-HaNA_1.01.02_3808_0131-line-474-1720-609-48", "date_scan": "NL-HaNA_1.01.02_3808_0131", "date_string": "Sabbathi den 10 Maart"}, {"inventory_num": 3808, "inventory_id": "NL-HaNA_1.01.02_3808", "session_date": "1753-03-12", "date": "1753-03-11", "date_line": "NL-HaNA_1.01.02_3808_0132-line-2569-1728-647-59", "date_scan": "NL-HaNA_1.01.02_3808_0132", "date_string": "Dominica den 11 Maart"}, {"inventory_num": 3808, "inventory_id": "NL-HaNA_1.01.02_3808", "session_date": "1753-03-12", "date": "1753-03-12", "date_line": "NL-HaNA_1.01.02_3808_0132-line-2615-1929-542-54", "date_scan": "NL-HaNA_1.01.02_3808_0132", "date_string": "Luna den 12 Maart"}, {"inventory_num": 3808, "inventory_id": "NL-HaNA_1.01.02_3808", "session_date": "1753-03-13", "date": "1753-03-13", "date_line": "NL-HaNA_1.01.02_3808_0133-line-1448-1365-575-55", "date_scan": "NL-HaNA_1.01.02_3808_0133", "date_string": "Martis den 13 Maart"}, {"inventory_num": 3808, "inventory_id": "NL-HaNA_1.01.02_3808", "session_date": "1753-03-14", "date": "1753-03-14", "date_line": "NL-HaNA_1.01.02_3808_0134-line-505-622-640-55", "date_scan": "NL-HaNA_1.01.02_3808_0134", "date_string": "Mercurii den 14 Maart"}, {"inventory_num": 3808, "inventory_id": "NL-HaNA_1.01.02_3808", "session_date": "1753-03-15", "date": "1753-03-15", "date_line": "NL-HaNA_1.01.02_3808_0134-line-2605-1384-560-61", "date_scan": "NL-HaNA_1.01.02_3808_0134", "date_string": "Jovis den 15 Maart"}, {"inventory_num": 3808, "inventory_id": "NL-HaNA_1.01.02_3808", "session_date": "1753-03-16", "date": "1753-03-16", "date_line": "NL-HaNA_1.01.02_3808_0136-line-2537-2275-585-68", "date_scan": "NL-HaNA_1.01.02_3808_0136", "date_string": "Veneris den 16 Maart"}, {"inventory_num": 3808, "inventory_id": "NL-HaNA_1.01.02_3808", "session_date": "1753-03-17", "date": "1753-03-17", "date_line": "NL-HaNA_1.01.02_3808_0138-line-2576-1372-610-53", "date_scan": "NL-HaNA_1.01.02_3808_0138", "date_string": "Sabbathi den 17 Maart"}, {"inventory_num": 3808, "inventory_id": "NL-HaNA_1.01.02_3808", "session_date": "1753-03-19", "date": "1753-03-18", "date_line": "NL-HaNA_1.01.02_3808_0139-line-469-2737-646-51", "date_scan": "NL-HaNA_1.01.02_3808_0139", "date_string": "Dominica den 18 Maart"}, {"inventory_num": 3808, "inventory_id": "NL-HaNA_1.01.02_3808", "session_date": "1753-03-19", "date": "1753-03-19", "date_line": "NL-HaNA_1.01.02_3808_0139-line-517-2937-546-63", "date_scan": "NL-HaNA_1.01.02_3808_0139", "date_string": "Luna den 19 Maart"}, {"inventory_num": 3808, "inventory_id": "NL-HaNA_1.01.02_3808", "session_date": "1753-03-20", "date": "1753-03-20", "date_line": "NL-HaNA_1.01.02_3808_0140-line-3581-638-577-58", "date_scan": "NL-HaNA_1.01.02_3808_0140", "date_string": "Martis den 20 Maart"}, {"inventory_num": 3808, "inventory_id": "NL-HaNA_1.01.02_3808", "session_date": "1753-03-21", "date": "1753-03-21", "date_line": "NL-HaNA_1.01.02_3808_0142-line-2590-1183-643-52", "date_scan": "NL-HaNA_1.01.02_3808_0142", "date_string": "Mercurii den 21 Maart"}, {"inventory_num": 3808, "inventory_id": "NL-HaNA_1.01.02_3808", "session_date": "1753-03-22", "date": "1753-03-22", "date_line": "NL-HaNA_1.01.02_3808_0144-line-2613-3016-541-56", "date_scan": "NL-HaNA_1.01.02_3808_0144", "date_string": "Jovis den 22 Maart"}, {"inventory_num": 3808, "inventory_id": "NL-HaNA_1.01.02_3808", "session_date": "1753-03-23", "date": "1753-03-23", "date_line": "NL-HaNA_1.01.02_3808_0145-line-3549-2592-580-54", "date_scan": "NL-HaNA_1.01.02_3808_0145", "date_string": "Veneris den 23 Maart"}, {"inventory_num": 3808, "inventory_id": "NL-HaNA_1.01.02_3808", "session_date": "1753-03-24", "date": "1753-03-24", "date_line": "NL-HaNA_1.01.02_3808_0146-line-2586-533-611-58", "date_scan": "NL-HaNA_1.01.02_3808_0146", "date_string": "Sabbathi den 24 Maart"}, {"inventory_num": 3808, "inventory_id": "NL-HaNA_1.01.02_3808", "session_date": "1753-03-26", "date": "1753-03-25", "date_line": "NL-HaNA_1.01.02_3808_0147-line-475-1657-645-61", "date_scan": "NL-HaNA_1.01.02_3808_0147", "date_string": "Dominica den 25 Maart"}, {"inventory_num": 3808, "inventory_id": "NL-HaNA_1.01.02_3808", "session_date": "1753-03-26", "date": "1753-03-26", "date_line": "NL-HaNA_1.01.02_3808_0147-line-516-1864-552-59", "date_scan": "NL-HaNA_1.01.02_3808_0147", "date_string": "Luna den 26 Maart"}, {"inventory_num": 3808, "inventory_id": "NL-HaNA_1.01.02_3808", "session_date": "1753-03-27", "date": "1753-03-27", "date_line": "NL-HaNA_1.01.02_3808_0148-line-530-2463-584-54", "date_scan": "NL-HaNA_1.01.02_3808_0148", "date_string": "Martis den 27 Maart"}, {"inventory_num": 3808, "inventory_id": "NL-HaNA_1.01.02_3808", "session_date": "1753-03-29", "date": "1753-03-28", "date_line": "NL-HaNA_1.01.02_3808_0149-line-3490-2338-634-57", "date_scan": "NL-HaNA_1.01.02_3808_0149", "date_string": "Mercurii den 28 Maart"}, {"inventory_num": 3808, "inventory_id": "NL-HaNA_1.01.02_3808", "session_date": "1753-03-29", "date": "1753-03-29", "date_line": "NL-HaNA_1.01.02_3808_0149-line-3549-2607-537-64", "date_scan": "NL-HaNA_1.01.02_3808_0149", "date_string": "Jovis den 29 Maart"}, {"inventory_num": 3808, "inventory_id": "NL-HaNA_1.01.02_3808", "session_date": "1753-03-30", "date": "1753-03-30", "date_line": "NL-HaNA_1.01.02_3808_0150-line-1428-1447-580-51", "date_scan": "NL-HaNA_1.01.02_3808_0150", "date_string": "Veneris den 30 Maart"}, {"inventory_num": 3808, "inventory_id": "NL-HaNA_1.01.02_3808", "session_date": "1753-03-31", "date": "1753-03-31", "date_line": "NL-HaNA_1.01.02_3808_0151-line-499-1816-619-55", "date_scan": "NL-HaNA_1.01.02_3808_0151", "date_string": "Sabbathi den 31 Maart"}, {"inventory_num": 3808, "inventory_id": "NL-HaNA_1.01.02_3808", "session_date": "1753-04-02", "date": "1753-04-01", "date_line": "NL-HaNA_1.01.02_3808_0152-line-465-1151-601-74", "date_scan": "NL-HaNA_1.01.02_3808_0152", "date_string": "Dominica den 1 April"}, {"inventory_num": 3808, "inventory_id": "NL-HaNA_1.01.02_3808", "session_date": "1753-04-02", "date": "1753-04-02", "date_line": "NL-HaNA_1.01.02_3808_0152-line-503-1347-507-62", "date_scan": "NL-HaNA_1.01.02_3808_0152", "date_string": "Luna den 2 April"}, {"inventory_num": 3808, "inventory_id": "NL-HaNA_1.01.02_3808", "session_date": "1753-04-03", "date": "1753-04-03", "date_line": "NL-HaNA_1.01.02_3808_0153-line-541-1064-532-62", "date_scan": "NL-HaNA_1.01.02_3808_0153", "date_string": "Martis den 3 April"}, {"inventory_num": 3808, "inventory_id": "NL-HaNA_1.01.02_3808", "session_date": "1753-04-04", "date": "1753-04-04", "date_line": "NL-HaNA_1.01.02_3808_0161-line-2525-1193-589-62", "date_scan": "NL-HaNA_1.01.02_3808_0161", "date_string": "Mercurii den 4 April"}, {"inventory_num": 3808, "inventory_id": "NL-HaNA_1.01.02_3808", "session_date": "1753-04-05", "date": "1753-04-05", "date_line": "NL-HaNA_1.01.02_3808_0162-line-3579-424-495-60", "date_scan": "NL-HaNA_1.01.02_3808_0162", "date_string": "Jovis den 5 April"}, {"inventory_num": 3808, "inventory_id": "NL-HaNA_1.01.02_3808", "session_date": "1753-04-06", "date": "1753-04-06", "date_line": "NL-HaNA_1.01.02_3808_0163-line-508-3109-537-59", "date_scan": "NL-HaNA_1.01.02_3808_0163", "date_string": "Veneris den 6 April"}, {"inventory_num": 3808, "inventory_id": "NL-HaNA_1.01.02_3808", "session_date": "1753-04-07", "date": "1753-04-07", "date_line": "NL-HaNA_1.01.02_3808_0164-line-1447-1099-571-62", "date_scan": "NL-HaNA_1.01.02_3808_0164", "date_string": "Sabbathi den 7 April"}, {"inventory_num": 3808, "inventory_id": "NL-HaNA_1.01.02_3808", "session_date": "1753-04-09", "date": "1753-04-08", "date_line": "NL-HaNA_1.01.02_3808_0165-line-2613-2107-596-62", "date_scan": "NL-HaNA_1.01.02_3808_0165", "date_string": "Dominica den 8 April"}, {"inventory_num": 3808, "inventory_id": "NL-HaNA_1.01.02_3808", "session_date": "1753-04-09", "date": "1753-04-09", "date_line": "NL-HaNA_1.01.02_3808_0165-line-2657-2299-502-61", "date_scan": "NL-HaNA_1.01.02_3808_0165", "date_string": "Luna den 9 April"}, {"inventory_num": 3808, "inventory_id": "NL-HaNA_1.01.02_3808", "session_date": "1753-04-10", "date": "1753-04-10", "date_line": "NL-HaNA_1.01.02_3808_0166-line-2643-1491-569-70", "date_scan": "NL-HaNA_1.01.02_3808_0166", "date_string": "Martis den 10 April"}, {"inventory_num": 3808, "inventory_id": "NL-HaNA_1.01.02_3808", "session_date": "1753-04-11", "date": "1753-04-11", "date_line": "NL-HaNA_1.01.02_3808_0168-line-1430-1854-640-76", "date_scan": "NL-HaNA_1.01.02_3808_0168", "date_string": "Mercurii den 11 April"}, {"inventory_num": 3808, "inventory_id": "NL-HaNA_1.01.02_3808", "session_date": "1753-04-12", "date": "1753-04-12", "date_line": "NL-HaNA_1.01.02_3808_0168-line-2627-1259-529-67", "date_scan": "NL-HaNA_1.01.02_3808_0168", "date_string": "Jovis den 12 April"}, {"inventory_num": 3808, "inventory_id": "NL-HaNA_1.01.02_3808", "session_date": "1753-04-13", "date": "1753-04-13", "date_line": "NL-HaNA_1.01.02_3808_0169-line-3544-1354-563-57", "date_scan": "NL-HaNA_1.01.02_3808_0169", "date_string": "Veneris den 13 April"}, {"inventory_num": 3808, "inventory_id": "NL-HaNA_1.01.02_3808", "session_date": "1753-04-14", "date": "1753-04-14", "date_line": "NL-HaNA_1.01.02_3808_0170-line-501-2184-595-61", "date_scan": "NL-HaNA_1.01.02_3808_0170", "date_string": "Sabbathi den 14 April"}, {"inventory_num": 3808, "inventory_id": "NL-HaNA_1.01.02_3808", "session_date": "1753-04-16", "date": "1753-04-15", "date_line": "NL-HaNA_1.01.02_3808_0172-line-3535-1221-624-67", "date_scan": "NL-HaNA_1.01.02_3808_0172", "date_string": "Dominica den 15 April"}, {"inventory_num": 3808, "inventory_id": "NL-HaNA_1.01.02_3808", "session_date": "1753-04-16", "date": "1753-04-16", "date_line": "NL-HaNA_1.01.02_3808_0172-line-3574-1402-528-64", "date_scan": "NL-HaNA_1.01.02_3808_0172", "date_string": "Luna den 16 April"}, {"inventory_num": 3808, "inventory_id": "NL-HaNA_1.01.02_3808", "session_date": "1753-04-17", "date": "1753-04-17", "date_line": "NL-HaNA_1.01.02_3808_0176-line-1491-1894-559-64", "date_scan": "NL-HaNA_1.01.02_3808_0176", "date_string": "Martis den 17 April"}, {"inventory_num": 3808, "inventory_id": "NL-HaNA_1.01.02_3808", "session_date": "1753-04-18", "date": "1753-04-18", "date_line": "NL-HaNA_1.01.02_3808_0177-line-1458-2744-620-61", "date_scan": "NL-HaNA_1.01.02_3808_0177", "date_string": "Mercurii den 18 April"}, {"inventory_num": 3808, "inventory_id": "NL-HaNA_1.01.02_3808", "session_date": "1753-04-19", "date": "1753-04-19", "date_line": "NL-HaNA_1.01.02_3808_0178-line-3589-353-521-63", "date_scan": "NL-HaNA_1.01.02_3808_0178", "date_string": "Jovis den 19 April"}, {"inventory_num": 3808, "inventory_id": "NL-HaNA_1.01.02_3808", "session_date": "1753-04-20", "date": "1753-04-20", "date_line": "NL-HaNA_1.01.02_3808_0178-line-3564-2052-564-63", "date_scan": "NL-HaNA_1.01.02_3808_0178", "date_string": "Veneris den 20 April"}, {"inventory_num": 3808, "inventory_id": "NL-HaNA_1.01.02_3808", "session_date": "1753-04-21", "date": "1753-04-21", "date_line": "NL-HaNA_1.01.02_3808_0180-line-475-3073-602-59", "date_scan": "NL-HaNA_1.01.02_3808_0180", "date_string": "Sabbathi den 21 April"}, {"inventory_num": 3808, "inventory_id": "NL-HaNA_1.01.02_3808", "session_date": "1753-04-24", "date": "1753-04-22", "date_line": "NL-HaNA_1.01.02_3808_0183-line-462-1581-636-65", "date_scan": "NL-HaNA_1.01.02_3808_0183", "date_string": "Dominica den 22 April"}, {"inventory_num": 3808, "inventory_id": "NL-HaNA_1.01.02_3808", "session_date": "1753-04-24", "date": "1753-04-23", "date_line": "NL-HaNA_1.01.02_3808_0183-line-505-1816-534-62", "date_scan": "NL-HaNA_1.01.02_3808_0183", "date_string": "Luna den 23 April"}, {"inventory_num": 3808, "inventory_id": "NL-HaNA_1.01.02_3808", "session_date": "1753-04-24", "date": "1753-04-24", "date_line": "NL-HaNA_1.01.02_3808_0183-line-518-2063-564-58", "date_scan": "NL-HaNA_1.01.02_3808_0183", "date_string": "Martis den 24 April"}, {"inventory_num": 3808, "inventory_id": "NL-HaNA_1.01.02_3808", "session_date": "1753-04-25", "date": "1753-04-25", "date_line": "NL-HaNA_1.01.02_3808_0185-line-1428-2352-618-62", "date_scan": "NL-HaNA_1.01.02_3808_0185", "date_string": "Mercurii den 25 April"}, {"inventory_num": 3808, "inventory_id": "NL-HaNA_1.01.02_3808", "session_date": "1753-04-26", "date": "1753-04-26", "date_line": "NL-HaNA_1.01.02_3808_0189-line-1464-1898-523-59", "date_scan": "NL-HaNA_1.01.02_3808_0189", "date_string": "Jovis den 26 April"}, {"inventory_num": 3808, "inventory_id": "NL-HaNA_1.01.02_3808", "session_date": "1753-04-27", "date": "1753-04-27", "date_line": "NL-HaNA_1.01.02_3808_0192-line-1460-481-568-60", "date_scan": "NL-HaNA_1.01.02_3808_0192", "date_string": "Veneris den 27 April"}, {"inventory_num": 3808, "inventory_id": "NL-HaNA_1.01.02_3808", "session_date": "1753-04-28", "date": "1753-04-28", "date_line": "NL-HaNA_1.01.02_3808_0194-line-3567-666-597-64", "date_scan": "NL-HaNA_1.01.02_3808_0194", "date_string": "Sabbathi den 28 April"}, {"inventory_num": 3808, "inventory_id": "NL-HaNA_1.01.02_3808", "session_date": "1753-04-30", "date": "1753-04-29", "date_line": "NL-HaNA_1.01.02_3808_0195-line-2586-868-629-62", "date_scan": "NL-HaNA_1.01.02_3808_0195", "date_string": "Dominica den 29 April"}, {"inventory_num": 3808, "inventory_id": "NL-HaNA_1.01.02_3808", "session_date": "1753-04-30", "date": "1753-04-30", "date_line": "NL-HaNA_1.01.02_3808_0195-line-2627-1052-526-64", "date_scan": "NL-HaNA_1.01.02_3808_0195", "date_string": "Luna den 30 April"}, {"inventory_num": 3808, "inventory_id": "NL-HaNA_1.01.02_3808", "session_date": "1753-05-01", "date": "1753-05-01", "date_line": "NL-HaNA_1.01.02_3808_0195-line-3608-1544-492-66", "date_scan": "NL-HaNA_1.01.02_3808_0195", "date_string": "Martis den 1 Mey"}, {"inventory_num": 3808, "inventory_id": "NL-HaNA_1.01.02_3808", "session_date": "1753-05-02", "date": "1753-05-02", "date_line": "NL-HaNA_1.01.02_3808_0197-line-2598-2832-555-60", "date_scan": "NL-HaNA_1.01.02_3808_0197", "date_string": "Mercurii den 2 Mey"}, {"inventory_num": 3808, "inventory_id": "NL-HaNA_1.01.02_3808", "session_date": "1753-05-03", "date": "1753-05-03", "date_line": "NL-HaNA_1.01.02_3808_0198-line-1562-2597-460-62", "date_scan": "NL-HaNA_1.01.02_3808_0198", "date_string": "Jovis den 3 Mey"}, {"inventory_num": 3808, "inventory_id": "NL-HaNA_1.01.02_3808", "session_date": "1753-05-04", "date": "1753-05-04", "date_line": "NL-HaNA_1.01.02_3808_0199-line-2610-2646-507-56", "date_scan": "NL-HaNA_1.01.02_3808_0199", "date_string": "Veneris den 4 Mey"}, {"inventory_num": 3808, "inventory_id": "NL-HaNA_1.01.02_3808", "session_date": "1753-05-05", "date": "1753-05-05", "date_line": "NL-HaNA_1.01.02_3808_0201-line-3561-2741-530-58", "date_scan": "NL-HaNA_1.01.02_3808_0201", "date_string": "Sabbathi den 5 Mey"}, {"inventory_num": 3808, "inventory_id": "NL-HaNA_1.01.02_3808", "session_date": "1753-05-07", "date": "1753-05-06", "date_line": "NL-HaNA_1.01.02_3808_0202-line-1441-1874-571-59", "date_scan": "NL-HaNA_1.01.02_3808_0202", "date_string": "Dominica den 6 Mey"}, {"inventory_num": 3808, "inventory_id": "NL-HaNA_1.01.02_3808", "session_date": "1753-05-07", "date": "1753-05-07", "date_line": "NL-HaNA_1.01.02_3808_0202-line-1489-2061-466-60", "date_scan": "NL-HaNA_1.01.02_3808_0202", "date_string": "Luna den 7 Mey"}, {"inventory_num": 3808, "inventory_id": "NL-HaNA_1.01.02_3808", "session_date": "1753-05-09", "date": "1753-05-08", "date_line": "NL-HaNA_1.01.02_3808_0203-line-1529-1271-499-60", "date_scan": "NL-HaNA_1.01.02_3808_0203", "date_string": "Martis den 8 Mey"}, {"inventory_num": 3808, "inventory_id": "NL-HaNA_1.01.02_3808", "session_date": "1753-05-09", "date": "1753-05-09", "date_line": "NL-HaNA_1.01.02_3808_0203-line-1488-1583-558-60", "date_scan": "NL-HaNA_1.01.02_3808_0203", "date_string": "Mercurii den 9 Mey"}, {"inventory_num": 3808, "inventory_id": "NL-HaNA_1.01.02_3808", "session_date": "1753-05-10", "date": "1753-05-10", "date_line": "NL-HaNA_1.01.02_3808_0206-line-544-1552-493-60", "date_scan": "NL-HaNA_1.01.02_3808_0206", "date_string": "Jovis den 10 Mey"}, {"inventory_num": 3808, "inventory_id": "NL-HaNA_1.01.02_3808", "session_date": "1753-05-11", "date": "1753-05-11", "date_line": "NL-HaNA_1.01.02_3808_0207-line-1470-712-535-54", "date_scan": "NL-HaNA_1.01.02_3808_0207", "date_string": "Veneris den 11 Mey"}, {"inventory_num": 3808, "inventory_id": "NL-HaNA_1.01.02_3808", "session_date": "1753-05-12", "date": "1753-05-12", "date_line": "NL-HaNA_1.01.02_3808_0209-line-458-2228-561-64", "date_scan": "NL-HaNA_1.01.02_3808_0209", "date_string": "Sabbathi den 12 Mey"}, {"inventory_num": 3808, "inventory_id": "NL-HaNA_1.01.02_3808", "session_date": "1753-05-14", "date": "1753-05-13", "date_line": "NL-HaNA_1.01.02_3808_0209-line-3511-953-594-66", "date_scan": "NL-HaNA_1.01.02_3808_0209", "date_string": "Dominica den 13 Mey"}, {"inventory_num": 3808, "inventory_id": "NL-HaNA_1.01.02_3808", "session_date": "1753-05-14", "date": "1753-05-14", "date_line": "NL-HaNA_1.01.02_3808_0209-line-3570-1147-499-63", "date_scan": "NL-HaNA_1.01.02_3808_0209", "date_string": "Luna den 14 Mey"}, {"inventory_num": 3808, "inventory_id": "NL-HaNA_1.01.02_3808", "session_date": "1753-05-15", "date": "1753-05-15", "date_line": "NL-HaNA_1.01.02_3808_0211-line-1484-1658-529-55", "date_scan": "NL-HaNA_1.01.02_3808_0211", "date_string": "Martis den 15 Mey"}, {"inventory_num": 3808, "inventory_id": "NL-HaNA_1.01.02_3808", "session_date": "1753-05-16", "date": "1753-05-16", "date_line": "NL-HaNA_1.01.02_3808_0214-line-505-1801-568-57", "date_scan": "NL-HaNA_1.01.02_3808_0214", "date_string": "Mercurii den 16 Mey"}, {"inventory_num": 3808, "inventory_id": "NL-HaNA_1.01.02_3808", "session_date": "1753-05-17", "date": "1753-05-17", "date_line": "NL-HaNA_1.01.02_3808_0214-line-2648-839-488-57", "date_scan": "NL-HaNA_1.01.02_3808_0214", "date_string": "Jovis den 17 Mey"}, {"inventory_num": 3808, "inventory_id": "NL-HaNA_1.01.02_3808", "session_date": "1753-05-18", "date": "1753-05-18", "date_line": "NL-HaNA_1.01.02_3808_0215-line-1501-712-531-55", "date_scan": "NL-HaNA_1.01.02_3808_0215", "date_string": "Veneris den 18 Mey"}, {"inventory_num": 3808, "inventory_id": "NL-HaNA_1.01.02_3808", "session_date": "1753-05-19", "date": "1753-05-19", "date_line": "NL-HaNA_1.01.02_3808_0217-line-487-1561-558-58", "date_scan": "NL-HaNA_1.01.02_3808_0217", "date_string": "Sabbathi den 19 Mey"}, {"inventory_num": 3808, "inventory_id": "NL-HaNA_1.01.02_3808", "session_date": "1753-05-21", "date": "1753-05-20", "date_line": "NL-HaNA_1.01.02_3808_0218-line-517-2930-590-55", "date_scan": "NL-HaNA_1.01.02_3808_0218", "date_string": "Dominica den 20 Mey"}, {"inventory_num": 3808, "inventory_id": "NL-HaNA_1.01.02_3808", "session_date": "1753-05-21", "date": "1753-05-21", "date_line": "NL-HaNA_1.01.02_3808_0218-line-581-3142-496-54", "date_scan": "NL-HaNA_1.01.02_3808_0218", "date_string": "Luna den 21 Mey"}, {"inventory_num": 3808, "inventory_id": "NL-HaNA_1.01.02_3808", "session_date": "1753-05-22", "date": "1753-05-22", "date_line": "NL-HaNA_1.01.02_3808_0219-line-574-1676-518-63", "date_scan": "NL-HaNA_1.01.02_3808_0219", "date_string": "Martis den 22 Mey"}, {"inventory_num": 3808, "inventory_id": "NL-HaNA_1.01.02_3808", "session_date": "1753-05-23", "date": "1753-05-23", "date_line": "NL-HaNA_1.01.02_3808_0221-line-502-2821-571-59", "date_scan": "NL-HaNA_1.01.02_3808_0221", "date_string": "Mercurii den 23 Mey"}, {"inventory_num": 3808, "inventory_id": "NL-HaNA_1.01.02_3808", "session_date": "1753-05-24", "date": "1753-05-24", "date_line": "NL-HaNA_1.01.02_3808_0221-line-2676-596-489-65", "date_scan": "NL-HaNA_1.01.02_3808_0221", "date_string": "Jovis den 24 Mey"}, {"inventory_num": 3808, "inventory_id": "NL-HaNA_1.01.02_3808", "session_date": "1753-05-25", "date": "1753-05-25", "date_line": "NL-HaNA_1.01.02_3808_0224-line-562-382-526-56", "date_scan": "NL-HaNA_1.01.02_3808_0224", "date_string": "Veneris den 25 Mey"}, {"inventory_num": 3808, "inventory_id": "NL-HaNA_1.01.02_3808", "session_date": "1753-05-26", "date": "1753-05-26", "date_line": "NL-HaNA_1.01.02_3808_0226-line-3600-2520-557-64", "date_scan": "NL-HaNA_1.01.02_3808_0226", "date_string": "Sabbathi den 26 Mey"}, {"inventory_num": 3808, "inventory_id": "NL-HaNA_1.01.02_3808", "session_date": "1753-05-28", "date": "1753-05-27", "date_line": "NL-HaNA_1.01.02_3808_0228-line-3582-1258-590-63", "date_scan": "NL-HaNA_1.01.02_3808_0228", "date_string": "Dominica den 27 Mey"}, {"inventory_num": 3808, "inventory_id": "NL-HaNA_1.01.02_3808", "session_date": "1753-05-28", "date": "1753-05-28", "date_line": "NL-HaNA_1.01.02_3808_0228-line-3646-1453-490-70", "date_scan": "NL-HaNA_1.01.02_3808_0228", "date_string": "Luna den 28 Mey"}, {"inventory_num": 3808, "inventory_id": "NL-HaNA_1.01.02_3808", "session_date": "1753-05-29", "date": "1753-05-29", "date_line": "NL-HaNA_1.01.02_3808_0229-line-2645-379-522-57", "date_scan": "NL-HaNA_1.01.02_3808_0229", "date_string": "Martis den 29 Mey"}, {"inventory_num": 3808, "inventory_id": "NL-HaNA_1.01.02_3808", "session_date": "1753-05-30", "date": "1753-05-30", "date_line": "NL-HaNA_1.01.02_3808_0230-line-2638-393-563-59", "date_scan": "NL-HaNA_1.01.02_3808_0230", "date_string": "Mercurii den 30 Mey"}, {"inventory_num": 3808, "inventory_id": "NL-HaNA_1.01.02_3808", "session_date": "1753-06-01", "date": "1753-05-31", "date_line": "NL-HaNA_1.01.02_3808_0232-line-3672-2535-483-58", "date_scan": "NL-HaNA_1.01.02_3808_0232", "date_string": "Jovis den 31 Mey"}, {"inventory_num": 3808, "inventory_id": "NL-HaNA_1.01.02_3808", "session_date": "1753-06-01", "date": "1753-06-01", "date_line": "NL-HaNA_1.01.02_3808_0232-line-3633-2794-526-57", "date_scan": "NL-HaNA_1.01.02_3808_0232", "date_string": "Veneris den 1 Juny"}, {"inventory_num": 3808, "inventory_id": "NL-HaNA_1.01.02_3808", "session_date": "1753-06-02", "date": "1753-06-02", "date_line": "NL-HaNA_1.01.02_3808_0234-line-2680-2311-546-58", "date_scan": "NL-HaNA_1.01.02_3808_0234", "date_string": "Sabbathi den 2 Juny"}, {"inventory_num": 3808, "inventory_id": "NL-HaNA_1.01.02_3808", "session_date": "1753-06-04", "date": "1753-06-03", "date_line": "NL-HaNA_1.01.02_3808_0236-line-2634-2051-577-54", "date_scan": "NL-HaNA_1.01.02_3808_0236", "date_string": "Dominica den 3 Juny"}, {"inventory_num": 3808, "inventory_id": "NL-HaNA_1.01.02_3808", "session_date": "1753-06-04", "date": "1753-06-04", "date_line": "NL-HaNA_1.01.02_3808_0236-line-2700-2238-479-61", "date_scan": "NL-HaNA_1.01.02_3808_0236", "date_string": "Luna den 4 Juny"}, {"inventory_num": 3808, "inventory_id": "NL-HaNA_1.01.02_3808", "session_date": "1753-06-05", "date": "1753-06-05", "date_line": "NL-HaNA_1.01.02_3808_0238-line-3610-960-507-67", "date_scan": "NL-HaNA_1.01.02_3808_0238", "date_string": "Martis den 5 Juny"}, {"inventory_num": 3808, "inventory_id": "NL-HaNA_1.01.02_3808", "session_date": "1753-06-06", "date": "1753-06-06", "date_line": "NL-HaNA_1.01.02_3808_0239-line-2642-3162-554-61", "date_scan": "NL-HaNA_1.01.02_3808_0239", "date_string": "Mercurii den 6 Juny"}, {"inventory_num": 3808, "inventory_id": "NL-HaNA_1.01.02_3808", "session_date": "1753-06-07", "date": "1753-06-07", "date_line": "NL-HaNA_1.01.02_3808_0240-line-2706-973-484-59", "date_scan": "NL-HaNA_1.01.02_3808_0240", "date_string": "Jovis den 7 Juny"}, {"inventory_num": 3808, "inventory_id": "NL-HaNA_1.01.02_3808", "session_date": "1753-06-08", "date": "1753-06-08", "date_line": "NL-HaNA_1.01.02_3808_0242-line-516-2498-525-60", "date_scan": "NL-HaNA_1.01.02_3808_0242", "date_string": "Veneris den 8 Juny"}, {"inventory_num": 3808, "inventory_id": "NL-HaNA_1.01.02_3808", "session_date": "1753-06-09", "date": "1753-06-09", "date_line": "NL-HaNA_1.01.02_3808_0243-line-509-1856-548-58", "date_scan": "NL-HaNA_1.01.02_3808_0243", "date_string": "Sabbathi den 9 Juny"}, {"inventory_num": 3808, "inventory_id": "NL-HaNA_1.01.02_3808", "session_date": "1753-06-12", "date": "1753-06-10", "date_line": "NL-HaNA_1.01.02_3808_0243-line-1425-2539-605-58", "date_scan": "NL-HaNA_1.01.02_3808_0243", "date_string": "Dominica den 10 Juny"}, {"inventory_num": 3808, "inventory_id": "NL-HaNA_1.01.02_3808", "session_date": "1753-06-12", "date": "1753-06-11", "date_line": "NL-HaNA_1.01.02_3808_0243-line-1484-2800-512-66", "date_scan": "NL-HaNA_1.01.02_3808_0243", "date_string": "Luna den 11 Juny"}, {"inventory_num": 3808, "inventory_id": "NL-HaNA_1.01.02_3808", "session_date": "1753-06-12", "date": "1753-06-12", "date_line": "NL-HaNA_1.01.02_3808_0243-line-1461-3057-539-64", "date_scan": "NL-HaNA_1.01.02_3808_0243", "date_string": "Martis den 12 Juny"}, {"inventory_num": 3808, "inventory_id": "NL-HaNA_1.01.02_3808", "session_date": "1753-06-13", "date": "1753-06-13", "date_line": "NL-HaNA_1.01.02_3808_0244-line-1460-2426-580-62", "date_scan": "NL-HaNA_1.01.02_3808_0244", "date_string": "Mercurii den 13 Juny"}, {"inventory_num": 3808, "inventory_id": "NL-HaNA_1.01.02_3808", "session_date": "1753-06-14", "date": "1753-06-14", "date_line": "NL-HaNA_1.01.02_3808_0245-line-2643-1113-502-61", "date_scan": "NL-HaNA_1.01.02_3808_0245", "date_string": "Jovis den 14 Juny"}, {"inventory_num": 3808, "inventory_id": "NL-HaNA_1.01.02_3808", "session_date": "1753-06-15", "date": "1753-06-15", "date_line": "NL-HaNA_1.01.02_3808_0246-line-576-3199-542-57", "date_scan": "NL-HaNA_1.01.02_3808_0246", "date_string": "Veneris den 15 Juny"}, {"inventory_num": 3808, "inventory_id": "NL-HaNA_1.01.02_3808", "session_date": "1753-06-16", "date": "1753-06-16", "date_line": "NL-HaNA_1.01.02_3808_0247-line-508-3148-583-61", "date_scan": "NL-HaNA_1.01.02_3808_0247", "date_string": "Sabbathi den 16 Juny"}, {"inventory_num": 3808, "inventory_id": "NL-HaNA_1.01.02_3808", "session_date": "1753-06-18", "date": "1753-06-17", "date_line": "NL-HaNA_1.01.02_3808_0248-line-1442-2558-611-57", "date_scan": "NL-HaNA_1.01.02_3808_0248", "date_string": "Dominica den 17 Juny"}, {"inventory_num": 3808, "inventory_id": "NL-HaNA_1.01.02_3808", "session_date": "1753-06-18", "date": "1753-06-18", "date_line": "NL-HaNA_1.01.02_3808_0248-line-1513-2754-510-59", "date_scan": "NL-HaNA_1.01.02_3808_0248", "date_string": "Luna den 18 Juny"}, {"inventory_num": 3808, "inventory_id": "NL-HaNA_1.01.02_3808", "session_date": "1753-06-19", "date": "1753-06-19", "date_line": "NL-HaNA_1.01.02_3808_0249-line-2585-3116-538-57", "date_scan": "NL-HaNA_1.01.02_3808_0249", "date_string": "Martis den 19 Juny"}, {"inventory_num": 3808, "inventory_id": "NL-HaNA_1.01.02_3808", "session_date": "1753-06-20", "date": "1753-06-20", "date_line": "NL-HaNA_1.01.02_3808_0251-line-499-435-576-57", "date_scan": "NL-HaNA_1.01.02_3808_0251", "date_string": "Mercurii den 20 Juny"}, {"inventory_num": 3808, "inventory_id": "NL-HaNA_1.01.02_3808", "session_date": "1753-06-21", "date": "1753-06-21", "date_line": "NL-HaNA_1.01.02_3808_0251-line-1512-2531-506-60", "date_scan": "NL-HaNA_1.01.02_3808_0251", "date_string": "Jovis den 21 Juny"}, {"inventory_num": 3808, "inventory_id": "NL-HaNA_1.01.02_3808", "session_date": "1753-06-22", "date": "1753-06-22", "date_line": "NL-HaNA_1.01.02_3808_0253-line-540-1324-549-59", "date_scan": "NL-HaNA_1.01.02_3808_0253", "date_string": "Veneris den 22 Juny"}, {"inventory_num": 3808, "inventory_id": "NL-HaNA_1.01.02_3808", "session_date": "1753-06-23", "date": "1753-06-23", "date_line": "NL-HaNA_1.01.02_3808_0253-line-3515-2758-581-67", "date_scan": "NL-HaNA_1.01.02_3808_0253", "date_string": "Sabbathi den 23 Juny"}, {"inventory_num": 3808, "inventory_id": "NL-HaNA_1.01.02_3808", "session_date": "1753-06-25", "date": "1753-06-24", "date_line": "NL-HaNA_1.01.02_3808_0254-line-3509-1395-609-59", "date_scan": "NL-HaNA_1.01.02_3808_0254", "date_string": "Dominica den 24 Juny"}, {"inventory_num": 3808, "inventory_id": "NL-HaNA_1.01.02_3808", "session_date": "1753-06-25", "date": "1753-06-25", "date_line": "NL-HaNA_1.01.02_3808_0254-line-3575-1580-513-61", "date_scan": "NL-HaNA_1.01.02_3808_0254", "date_string": "Luna den 25 Juny"}, {"inventory_num": 3808, "inventory_id": "NL-HaNA_1.01.02_3808", "session_date": "1753-06-26", "date": "1753-06-26", "date_line": "NL-HaNA_1.01.02_3808_0256-line-3509-1613-540-64", "date_scan": "NL-HaNA_1.01.02_3808_0256", "date_string": "Martis den 26 Juny"}, {"inventory_num": 3808, "inventory_id": "NL-HaNA_1.01.02_3808", "session_date": "1753-06-27", "date": "1753-06-27", "date_line": "NL-HaNA_1.01.02_3808_0257-line-3492-1547-584-58", "date_scan": "NL-HaNA_1.01.02_3808_0257", "date_string": "Mercurii den 27 Juny"}, {"inventory_num": 3808, "inventory_id": "NL-HaNA_1.01.02_3808", "session_date": "1753-06-28", "date": "1753-06-28", "date_line": "NL-HaNA_1.01.02_3808_0258-line-3525-1023-509-62", "date_scan": "NL-HaNA_1.01.02_3808_0258", "date_string": "Jovis den 28 Juny"}, {"inventory_num": 3808, "inventory_id": "NL-HaNA_1.01.02_3808", "session_date": "1753-06-29", "date": "1753-06-29", "date_line": "NL-HaNA_1.01.02_3808_0259-line-1494-1310-550-57", "date_scan": "NL-HaNA_1.01.02_3808_0259", "date_string": "Veneris den 29 Juny"}, {"inventory_num": 3808, "inventory_id": "NL-HaNA_1.01.02_3808", "session_date": "1753-06-30", "date": "1753-06-30", "date_line": "NL-HaNA_1.01.02_3808_0259-line-3494-1558-579-60", "date_scan": "NL-HaNA_1.01.02_3808_0259", "date_string": "Sabbathi den 30 Juny"}, {"inventory_num": 3808, "inventory_id": "NL-HaNA_1.01.02_3808", "session_date": "1753-07-03", "date": "1753-07-03", "date_line": "NL-HaNA_1.01.02_3808_0266-line-1512-1878-501-62", "date_scan": "NL-HaNA_1.01.02_3808_0266", "date_string": "Martis den 3 July"}, {"inventory_num": 3808, "inventory_id": "NL-HaNA_1.01.02_3808", "session_date": "1753-07-04", "date": "1753-07-04", "date_line": "NL-HaNA_1.01.02_3808_0268-line-1517-390-546-60", "date_scan": "NL-HaNA_1.01.02_3808_0268", "date_string": "Mercurii den 4 July"}, {"inventory_num": 3808, "inventory_id": "NL-HaNA_1.01.02_3808", "session_date": "1753-07-05", "date": "1753-07-05", "date_line": "NL-HaNA_1.01.02_3808_0269-line-3638-2962-465-61", "date_scan": "NL-HaNA_1.01.02_3808_0269", "date_string": "Jovis den 5 July"}, {"inventory_num": 3808, "inventory_id": "NL-HaNA_1.01.02_3808", "session_date": "1753-07-06", "date": "1753-07-06", "date_line": "NL-HaNA_1.01.02_3808_0270-line-578-1512-514-59", "date_scan": "NL-HaNA_1.01.02_3808_0270", "date_string": "Veneris den 6 July"}, {"inventory_num": 3808, "inventory_id": "NL-HaNA_1.01.02_3808", "session_date": "1753-07-07", "date": "1753-07-07", "date_line": "NL-HaNA_1.01.02_3808_0272-line-1483-1995-547-59", "date_scan": "NL-HaNA_1.01.02_3808_0272", "date_string": "Sabbathi den 7 July"}, {"inventory_num": 3808, "inventory_id": "NL-HaNA_1.01.02_3808", "session_date": "1753-07-09", "date": "1753-07-08", "date_line": "NL-HaNA_1.01.02_3808_0273-line-3475-694-573-58", "date_scan": "NL-HaNA_1.01.02_3808_0273", "date_string": "Dominica den 8 July"}, {"inventory_num": 3808, "inventory_id": "NL-HaNA_1.01.02_3808", "session_date": "1753-07-09", "date": "1753-07-09", "date_line": "NL-HaNA_1.01.02_3808_0273-line-3539-888-475-60", "date_scan": "NL-HaNA_1.01.02_3808_0273", "date_string": "Luna den 9 July"}, {"inventory_num": 3808, "inventory_id": "NL-HaNA_1.01.02_3808", "session_date": "1753-07-10", "date": "1753-07-10", "date_line": "NL-HaNA_1.01.02_3808_0275-line-1509-452-521-58", "date_scan": "NL-HaNA_1.01.02_3808_0275", "date_string": "Martis den 10 July"}, {"inventory_num": 3808, "inventory_id": "NL-HaNA_1.01.02_3808", "session_date": "1753-07-11", "date": "1753-07-11", "date_line": "NL-HaNA_1.01.02_3808_0279-line-521-1099-577-54", "date_scan": "NL-HaNA_1.01.02_3808_0279", "date_string": "Mercurii den 11 July"}, {"inventory_num": 3808, "inventory_id": "NL-HaNA_1.01.02_3808", "session_date": "1753-07-12", "date": "1753-07-12", "date_line": "NL-HaNA_1.01.02_3808_0280-line-600-550-499-62", "date_scan": "NL-HaNA_1.01.02_3808_0280", "date_string": "Jovis den 12 July"}, {"inventory_num": 3808, "inventory_id": "NL-HaNA_1.01.02_3808", "session_date": "1753-07-13", "date": "1753-07-13", "date_line": "NL-HaNA_1.01.02_3808_0283-line-1488-2527-538-59", "date_scan": "NL-HaNA_1.01.02_3808_0283", "date_string": "Veneris den 13 July"}, {"inventory_num": 3808, "inventory_id": "NL-HaNA_1.01.02_3808", "session_date": "1753-07-14", "date": "1753-07-14", "date_line": "NL-HaNA_1.01.02_3808_0285-line-1479-662-573-58", "date_scan": "NL-HaNA_1.01.02_3808_0285", "date_string": "Sabbathi den 14 July"}, {"inventory_num": 3808, "inventory_id": "NL-HaNA_1.01.02_3808", "session_date": "1753-07-16", "date": "1753-07-15", "date_line": "NL-HaNA_1.01.02_3808_0286-line-1413-1717-594-57", "date_scan": "NL-HaNA_1.01.02_3808_0286", "date_string": "Dominica den 15 July"}, {"inventory_num": 3808, "inventory_id": "NL-HaNA_1.01.02_3808", "session_date": "1753-07-16", "date": "1753-07-16", "date_line": "NL-HaNA_1.01.02_3808_0286-line-1452-1907-499-57", "date_scan": "NL-HaNA_1.01.02_3808_0286", "date_string": "Luna den 16 July"}, {"inventory_num": 3808, "inventory_id": "NL-HaNA_1.01.02_3808", "session_date": "1753-07-17", "date": "1753-07-17", "date_line": "NL-HaNA_1.01.02_3808_0288-line-551-2430-536-59", "date_scan": "NL-HaNA_1.01.02_3808_0288", "date_string": "Martis den 17 July"}, {"inventory_num": 3808, "inventory_id": "NL-HaNA_1.01.02_3808", "session_date": "1753-07-18", "date": "1753-07-18", "date_line": "NL-HaNA_1.01.02_3808_0289-line-3526-374-573-61", "date_scan": "NL-HaNA_1.01.02_3808_0289", "date_string": "Mercurii den 18 July"}, {"inventory_num": 3808, "inventory_id": "NL-HaNA_1.01.02_3808", "session_date": "1753-07-19", "date": "1753-07-19", "date_line": "NL-HaNA_1.01.02_3808_0290-line-536-1011-497-69", "date_scan": "NL-HaNA_1.01.02_3808_0290", "date_string": "Jovis den 19 July"}, {"inventory_num": 3808, "inventory_id": "NL-HaNA_1.01.02_3808", "session_date": "1753-07-20", "date": "1753-07-20", "date_line": "NL-HaNA_1.01.02_3808_0291-line-1432-756-545-60", "date_scan": "NL-HaNA_1.01.02_3808_0291", "date_string": "Veneris den 20 July"}, {"inventory_num": 3808, "inventory_id": "NL-HaNA_1.01.02_3808", "session_date": "1753-07-21", "date": "1753-07-21", "date_line": "NL-HaNA_1.01.02_3808_0312-line-3504-1730-577-60", "date_scan": "NL-HaNA_1.01.02_3808_0312", "date_string": "Sabbathi den 21 July"}, {"inventory_num": 3808, "inventory_id": "NL-HaNA_1.01.02_3808", "session_date": "1753-07-23", "date": "1753-07-22", "date_line": "NL-HaNA_1.01.02_3808_0313-line-3514-2116-602-61", "date_scan": "NL-HaNA_1.01.02_3808_0313", "date_string": "Dominica den 22 July"}, {"inventory_num": 3808, "inventory_id": "NL-HaNA_1.01.02_3808", "session_date": "1753-07-23", "date": "1753-07-23", "date_line": "NL-HaNA_1.01.02_3808_0313-line-3555-2306-500-60", "date_scan": "NL-HaNA_1.01.02_3808_0313", "date_string": "Luna den 23 July"}, {"inventory_num": 3808, "inventory_id": "NL-HaNA_1.01.02_3808", "session_date": "1753-07-24", "date": "1753-07-24", "date_line": "NL-HaNA_1.01.02_3808_0314-line-3580-938-526-62", "date_scan": "NL-HaNA_1.01.02_3808_0314", "date_string": "Martis den 24 July"}, {"inventory_num": 3808, "inventory_id": "NL-HaNA_1.01.02_3808", "session_date": "1753-07-25", "date": "1753-07-25", "date_line": "NL-HaNA_1.01.02_3808_0316-line-443-511-578-58", "date_scan": "NL-HaNA_1.01.02_3808_0316", "date_string": "Mercurii den 25 July"}, {"inventory_num": 3808, "inventory_id": "NL-HaNA_1.01.02_3808", "session_date": "1753-07-26", "date": "1753-07-26", "date_line": "NL-HaNA_1.01.02_3808_0317-line-565-3190-497-59", "date_scan": "NL-HaNA_1.01.02_3808_0317", "date_string": "Jovis den 26 July"}, {"inventory_num": 3808, "inventory_id": "NL-HaNA_1.01.02_3808", "session_date": "1753-07-27", "date": "1753-07-27", "date_line": "NL-HaNA_1.01.02_3808_0318-line-1462-1646-543-58", "date_scan": "NL-HaNA_1.01.02_3808_0318", "date_string": "Veneris den 27 July"}, {"inventory_num": 3808, "inventory_id": "NL-HaNA_1.01.02_3808", "session_date": "1753-07-28", "date": "1753-07-28", "date_line": "NL-HaNA_1.01.02_3808_0319-line-480-2158-572-70", "date_scan": "NL-HaNA_1.01.02_3808_0319", "date_string": "Sabbathi den 28 July"}, {"inventory_num": 3808, "inventory_id": "NL-HaNA_1.01.02_3808", "session_date": "1753-07-30", "date": "1753-07-29", "date_line": "NL-HaNA_1.01.02_3808_0320-line-1432-1917-604-57", "date_scan": "NL-HaNA_1.01.02_3808_0320", "date_string": "Dominica den 29 July"}, {"inventory_num": 3808, "inventory_id": "NL-HaNA_1.01.02_3808", "session_date": "1753-07-30", "date": "1753-07-30", "date_line": "NL-HaNA_1.01.02_3808_0320-line-1470-2113-505-59", "date_scan": "NL-HaNA_1.01.02_3808_0320", "date_string": "Luna den 30 July"}, {"inventory_num": 3808, "inventory_id": "NL-HaNA_1.01.02_3808", "session_date": "1753-07-31", "date": "1753-07-31", "date_line": "NL-HaNA_1.01.02_3808_0321-line-498-2283-534-56", "date_scan": "NL-HaNA_1.01.02_3808_0321", "date_string": "Martis den 31 July"}, {"inventory_num": 3808, "inventory_id": "NL-HaNA_1.01.02_3808", "session_date": "1753-08-01", "date": "1753-08-01", "date_line": "NL-HaNA_1.01.02_3808_0322-line-3480-1266-621-64", "date_scan": "NL-HaNA_1.01.02_3808_0322", "date_string": "Mercurii den 1 Augusti"}, {"inventory_num": 3808, "inventory_id": "NL-HaNA_1.01.02_3808", "session_date": "1753-08-02", "date": "1753-08-02", "date_line": "NL-HaNA_1.01.02_3808_0325-line-1520-3079-546-63", "date_scan": "NL-HaNA_1.01.02_3808_0325", "date_string": "Jovis den 2 Augusti"}, {"inventory_num": 3808, "inventory_id": "NL-HaNA_1.01.02_3808", "session_date": "1753-08-03", "date": "1753-08-03", "date_line": "NL-HaNA_1.01.02_3808_0325-line-2583-2979-584-61", "date_scan": "NL-HaNA_1.01.02_3808_0325", "date_string": "Veneris den 3 Augusti"}, {"inventory_num": 3808, "inventory_id": "NL-HaNA_1.01.02_3808", "session_date": "1753-08-06", "date": "1753-08-04", "date_line": "NL-HaNA_1.01.02_3808_0326-line-1398-1984-620-62", "date_scan": "NL-HaNA_1.01.02_3808_0326", "date_string": "Sabbathi den 4 Augusti"}, {"inventory_num": 3808, "inventory_id": "NL-HaNA_1.01.02_3808", "session_date": "1753-08-06", "date": "1753-08-05", "date_line": "NL-HaNA_1.01.02_3808_0326-line-1389-2188-659-62", "date_scan": "NL-HaNA_1.01.02_3808_0326", "date_string": "Dominica den 5 Augusti"}, {"inventory_num": 3808, "inventory_id": "NL-HaNA_1.01.02_3808", "session_date": "1753-08-06", "date": "1753-08-06", "date_line": "NL-HaNA_1.01.02_3808_0326-line-1441-2392-555-61", "date_scan": "NL-HaNA_1.01.02_3808_0326", "date_string": "Luna den 6 Augusti"}, {"inventory_num": 3808, "inventory_id": "NL-HaNA_1.01.02_3808", "session_date": "1753-08-07", "date": "1753-08-07", "date_line": "NL-HaNA_1.01.02_3808_0327-line-3537-1079-601-69", "date_scan": "NL-HaNA_1.01.02_3808_0327", "date_string": "Martis den 7 Augusti"}, {"inventory_num": 3808, "inventory_id": "NL-HaNA_1.01.02_3808", "session_date": "1753-08-08", "date": "1753-08-08", "date_line": "NL-HaNA_1.01.02_3808_0329-line-1447-2169-621-67", "date_scan": "NL-HaNA_1.01.02_3808_0329", "date_string": "Mercurii den 8 Augusti"}, {"inventory_num": 3808, "inventory_id": "NL-HaNA_1.01.02_3808", "session_date": "1753-08-09", "date": "1753-08-09", "date_line": "NL-HaNA_1.01.02_3808_0331-line-571-2046-545-61", "date_scan": "NL-HaNA_1.01.02_3808_0331", "date_string": "Jovis den 9 Augusti"}, {"inventory_num": 3808, "inventory_id": "NL-HaNA_1.01.02_3808", "session_date": "1753-08-10", "date": "1753-08-10", "date_line": "NL-HaNA_1.01.02_3808_0332-line-537-1214-611-62", "date_scan": "NL-HaNA_1.01.02_3808_0332", "date_string": "Veneris den 10 Augusti"}, {"inventory_num": 3808, "inventory_id": "NL-HaNA_1.01.02_3808", "session_date": "1753-08-13", "date": "1753-08-12", "date_line": "NL-HaNA_1.01.02_3808_0334-line-436-606-680-61", "date_scan": "NL-HaNA_1.01.02_3808_0334", "date_string": "Dominica den 12 Augusti"}, {"inventory_num": 3808, "inventory_id": "NL-HaNA_1.01.02_3808", "session_date": "1753-08-13", "date": "1753-08-13", "date_line": "NL-HaNA_1.01.02_3808_0334-line-483-804-579-60", "date_scan": "NL-HaNA_1.01.02_3808_0334", "date_string": "Luna den 13 Augusti"}, {"inventory_num": 3808, "inventory_id": "NL-HaNA_1.01.02_3808", "session_date": "1753-08-14", "date": "1753-08-14", "date_line": "NL-HaNA_1.01.02_3808_0335-line-1414-2348-612-60", "date_scan": "NL-HaNA_1.01.02_3808_0335", "date_string": "Martis den 14 Augusti"}, {"inventory_num": 3808, "inventory_id": "NL-HaNA_1.01.02_3808", "session_date": "1753-08-15", "date": "1753-08-15", "date_line": "NL-HaNA_1.01.02_3808_0336-line-3420-768-647-67", "date_scan": "NL-HaNA_1.01.02_3808_0336", "date_string": "Mercurii den 15 Augusti"}, {"inventory_num": 3808, "inventory_id": "NL-HaNA_1.01.02_3808", "session_date": "1753-08-16", "date": "1753-08-16", "date_line": "NL-HaNA_1.01.02_3808_0339-line-3467-848-570-63", "date_scan": "NL-HaNA_1.01.02_3808_0339", "date_string": "Jovis den 16 Augusti"}, {"inventory_num": 3808, "inventory_id": "NL-HaNA_1.01.02_3808", "session_date": "1753-08-17", "date": "1753-08-17", "date_line": "NL-HaNA_1.01.02_3808_0340-line-2569-1354-615-59", "date_scan": "NL-HaNA_1.01.02_3808_0340", "date_string": "Veneris den 17 Augusti"}, {"inventory_num": 3808, "inventory_id": "NL-HaNA_1.01.02_3808", "session_date": "1753-08-20", "date": "1753-08-18", "date_line": "NL-HaNA_1.01.02_3808_0342-line-517-856-644-58", "date_scan": "NL-HaNA_1.01.02_3808_0342", "date_string": "Sabbathi den 18 Augusti"}, {"inventory_num": 3808, "inventory_id": "NL-HaNA_1.01.02_3808", "session_date": "1753-08-20", "date": "1753-08-19", "date_line": "NL-HaNA_1.01.02_3808_0342-line-515-1062-668-60", "date_scan": "NL-HaNA_1.01.02_3808_0342", "date_string": "Dominica den 19 Augusti"}, {"inventory_num": 3808, "inventory_id": "NL-HaNA_1.01.02_3808", "session_date": "1753-08-20", "date": "1753-08-20", "date_line": "NL-HaNA_1.01.02_3808_0342-line-555-1247-572-71", "date_scan": "NL-HaNA_1.01.02_3808_0342", "date_string": "Luna den 20 Augusti"}, {"inventory_num": 3808, "inventory_id": "NL-HaNA_1.01.02_3808", "session_date": "1753-08-21", "date": "1753-08-21", "date_line": "NL-HaNA_1.01.02_3808_0345-line-476-2917-608-62", "date_scan": "NL-HaNA_1.01.02_3808_0345", "date_string": "Martis den 21 Augusti"}, {"inventory_num": 3808, "inventory_id": "NL-HaNA_1.01.02_3808", "session_date": "1753-08-22", "date": "1753-08-22", "date_line": "NL-HaNA_1.01.02_3808_0346-line-3463-1267-648-64", "date_scan": "NL-HaNA_1.01.02_3808_0346", "date_string": "Mercurii den 22 Augusti"}, {"inventory_num": 3808, "inventory_id": "NL-HaNA_1.01.02_3808", "session_date": "1753-08-23", "date": "1753-08-23", "date_line": "NL-HaNA_1.01.02_3808_0347-line-518-2067-570-63", "date_scan": "NL-HaNA_1.01.02_3808_0347", "date_string": "Jovis den 23 Augusti"}, {"inventory_num": 3808, "inventory_id": "NL-HaNA_1.01.02_3808", "session_date": "1753-08-24", "date": "1753-08-24", "date_line": "NL-HaNA_1.01.02_3808_0348-line-531-2951-612-60", "date_scan": "NL-HaNA_1.01.02_3808_0348", "date_string": "Veneris den 24 Augusti"}, {"inventory_num": 3808, "inventory_id": "NL-HaNA_1.01.02_3808", "session_date": "1753-08-27", "date": "1753-08-25", "date_line": "NL-HaNA_1.01.02_3808_0349-line-489-643-640-62", "date_scan": "NL-HaNA_1.01.02_3808_0349", "date_string": "Sabbathi den 25 Augusti"}, {"inventory_num": 3808, "inventory_id": "NL-HaNA_1.01.02_3808", "session_date": "1753-08-27", "date": "1753-08-26", "date_line": "NL-HaNA_1.01.02_3808_0349-line-487-854-671-60", "date_scan": "NL-HaNA_1.01.02_3808_0349", "date_string": "Dominica den 26 Augusti"}, {"inventory_num": 3808, "inventory_id": "NL-HaNA_1.01.02_3808", "session_date": "1753-08-27", "date": "1753-08-27", "date_line": "NL-HaNA_1.01.02_3808_0349-line-527-1043-575-60", "date_scan": "NL-HaNA_1.01.02_3808_0349", "date_string": "Luna den 27 Augusti"}, {"inventory_num": 3808, "inventory_id": "NL-HaNA_1.01.02_3808", "session_date": "1753-08-28", "date": "1753-08-28", "date_line": "NL-HaNA_1.01.02_3808_0350-line-460-1312-615-60", "date_scan": "NL-HaNA_1.01.02_3808_0350", "date_string": "Martis den 28 Augusti"}, {"inventory_num": 3808, "inventory_id": "NL-HaNA_1.01.02_3808", "session_date": "1753-08-29", "date": "1753-08-29", "date_line": "NL-HaNA_1.01.02_3808_0350-line-2484-672-652-61", "date_scan": "NL-HaNA_1.01.02_3808_0350", "date_string": "Mercurii den 29 Augusti"}, {"inventory_num": 3808, "inventory_id": "NL-HaNA_1.01.02_3808", "session_date": "1753-08-30", "date": "1753-08-30", "date_line": "NL-HaNA_1.01.02_3808_0352-line-483-3097-577-60", "date_scan": "NL-HaNA_1.01.02_3808_0352", "date_string": "Jovis den 30 Augusti"}, {"inventory_num": 3808, "inventory_id": "NL-HaNA_1.01.02_3808", "session_date": "1753-08-31", "date": "1753-08-31", "date_line": "NL-HaNA_1.01.02_3808_0352-line-2524-2599-610-62", "date_scan": "NL-HaNA_1.01.02_3808_0352", "date_string": "Veneris den 31 Augusti"}, {"inventory_num": 3808, "inventory_id": "NL-HaNA_1.01.02_3808", "session_date": "1753-09-03", "date": "1753-09-01", "date_line": "NL-HaNA_1.01.02_3808_0356-line-1379-3132-676-64", "date_scan": "NL-HaNA_1.01.02_3808_0356", "date_string": "Sabbathi den 1 September"}, {"inventory_num": 3808, "inventory_id": "NL-HaNA_1.01.02_3808", "session_date": "1753-09-03", "date": "1753-09-02", "date_line": "NL-HaNA_1.01.02_3808_0356-line-2499-429-702-66", "date_scan": "NL-HaNA_1.01.02_3808_0356", "date_string": "Dominica den 2 September"}, {"inventory_num": 3808, "inventory_id": "NL-HaNA_1.01.02_3808", "session_date": "1753-09-03", "date": "1753-09-03", "date_line": "NL-HaNA_1.01.02_3808_0356-line-2546-621-608-60", "date_scan": "NL-HaNA_1.01.02_3808_0356", "date_string": "Luna den 3 September"}, {"inventory_num": 3808, "inventory_id": "NL-HaNA_1.01.02_3808", "session_date": "1753-09-04", "date": "1753-09-04", "date_line": "NL-HaNA_1.01.02_3808_0359-line-529-427-623-60", "date_scan": "NL-HaNA_1.01.02_3808_0359", "date_string": "Martis den 4 September"}, {"inventory_num": 3808, "inventory_id": "NL-HaNA_1.01.02_3808", "session_date": "1753-09-05", "date": "1753-09-05", "date_line": "NL-HaNA_1.01.02_3808_0359-line-3474-1715-674-64", "date_scan": "NL-HaNA_1.01.02_3808_0359", "date_string": "Mercurii den 5 September"}, {"inventory_num": 3808, "inventory_id": "NL-HaNA_1.01.02_3808", "session_date": "1753-09-06", "date": "1753-09-06", "date_line": "NL-HaNA_1.01.02_3808_0361-line-1482-2242-599-62", "date_scan": "NL-HaNA_1.01.02_3808_0361", "date_string": "Jovis den 6 September"}, {"inventory_num": 3808, "inventory_id": "NL-HaNA_1.01.02_3808", "session_date": "1753-09-07", "date": "1753-09-07", "date_line": "NL-HaNA_1.01.02_3808_0362-line-515-1910-643-62", "date_scan": "NL-HaNA_1.01.02_3808_0362", "date_string": "Veneris den 7 September"}, {"inventory_num": 3808, "inventory_id": "NL-HaNA_1.01.02_3808", "session_date": "1753-09-10", "date": "1753-09-08", "date_line": "NL-HaNA_1.01.02_3808_0363-line-3511-2468-675-60", "date_scan": "NL-HaNA_1.01.02_3808_0363", "date_string": "Sabbathi den 8 September"}, {"inventory_num": 3808, "inventory_id": "NL-HaNA_1.01.02_3808", "session_date": "1753-09-10", "date": "1753-09-09", "date_line": "NL-HaNA_1.01.02_3808_0363-line-3505-2675-697-61", "date_scan": "NL-HaNA_1.01.02_3808_0363", "date_string": "Dominica den 9 September"}, {"inventory_num": 3808, "inventory_id": "NL-HaNA_1.01.02_3808", "session_date": "1753-09-10", "date": "1753-09-10", "date_line": "NL-HaNA_1.01.02_3808_0363-line-3520-2859-630-62", "date_scan": "NL-HaNA_1.01.02_3808_0363", "date_string": "Luna den 10 September"}, {"inventory_num": 3808, "inventory_id": "NL-HaNA_1.01.02_3808", "session_date": "1753-09-11", "date": "1753-09-11", "date_line": "NL-HaNA_1.01.02_3808_0365-line-1451-871-656-65", "date_scan": "NL-HaNA_1.01.02_3808_0365", "date_string": "Martis den 11 September"}, {"inventory_num": 3808, "inventory_id": "NL-HaNA_1.01.02_3808", "session_date": "1753-09-12", "date": "1753-09-12", "date_line": "NL-HaNA_1.01.02_3808_0365-line-2533-1021-708-62", "date_scan": "NL-HaNA_1.01.02_3808_0365", "date_string": "Mercurii den 12 September"}, {"inventory_num": 3808, "inventory_id": "NL-HaNA_1.01.02_3808", "session_date": "1753-09-13", "date": "1753-09-13", "date_line": "NL-HaNA_1.01.02_3808_0366-line-1440-1317-635-67", "date_scan": "NL-HaNA_1.01.02_3808_0366", "date_string": "Jovis den 13 September"}, {"inventory_num": 3808, "inventory_id": "NL-HaNA_1.01.02_3808", "session_date": "1753-09-14", "date": "1753-09-14", "date_line": "NL-HaNA_1.01.02_3808_0366-line-2506-2111-669-61", "date_scan": "NL-HaNA_1.01.02_3808_0366", "date_string": "Veneris den 14 September"}, {"inventory_num": 3808, "inventory_id": "NL-HaNA_1.01.02_3808", "session_date": "1753-09-17", "date": "1753-09-15", "date_line": "NL-HaNA_1.01.02_3808_0367-line-3464-1790-692-66", "date_scan": "NL-HaNA_1.01.02_3808_0367", "date_string": "Sabbathi den 15 September"}, {"inventory_num": 3808, "inventory_id": "NL-HaNA_1.01.02_3808", "session_date": "1753-09-17", "date": "1753-09-16", "date_line": "NL-HaNA_1.01.02_3808_0367-line-3459-1975-724-62", "date_scan": "NL-HaNA_1.01.02_3808_0367", "date_string": "Dominica den 16 September"}, {"inventory_num": 3808, "inventory_id": "NL-HaNA_1.01.02_3808", "session_date": "1753-09-17", "date": "1753-09-17", "date_line": "NL-HaNA_1.01.02_3808_0367-line-3505-2132-623-64", "date_scan": "NL-HaNA_1.01.02_3808_0367", "date_string": "Luna den 17 September"}, {"inventory_num": 3808, "inventory_id": "NL-HaNA_1.01.02_3808", "session_date": "1753-09-18", "date": "1753-09-18", "date_line": "NL-HaNA_1.01.02_3808_0369-line-1444-3058-649-69", "date_scan": "NL-HaNA_1.01.02_3808_0369", "date_string": "Martis den 18 September"}, {"inventory_num": 3808, "inventory_id": "NL-HaNA_1.01.02_3808", "session_date": "1753-09-19", "date": "1753-09-19", "date_line": "NL-HaNA_1.01.02_3808_0370-line-1420-3213-697-73", "date_scan": "NL-HaNA_1.01.02_3808_0370", "date_string": "Mercurii den 19 September"}, {"inventory_num": 3808, "inventory_id": "NL-HaNA_1.01.02_3808", "session_date": "1753-09-20", "date": "1753-09-20", "date_line": "NL-HaNA_1.01.02_3808_0371-line-3492-401-628-60", "date_scan": "NL-HaNA_1.01.02_3808_0371", "date_string": "Jovis den 20 September"}, {"inventory_num": 3808, "inventory_id": "NL-HaNA_1.01.02_3808", "session_date": "1753-09-21", "date": "1753-09-21", "date_line": "NL-HaNA_1.01.02_3808_0372-line-408-3170-667-61", "date_scan": "NL-HaNA_1.01.02_3808_0372", "date_string": "Veneris den 21 September"}, {"inventory_num": 3808, "inventory_id": "NL-HaNA_1.01.02_3808", "session_date": "1753-09-24", "date": "1753-09-22", "date_line": "NL-HaNA_1.01.02_3808_0372-line-1349-2537-703-64", "date_scan": "NL-HaNA_1.01.02_3808_0372", "date_string": "Sabbathi den 22 September"}, {"inventory_num": 3808, "inventory_id": "NL-HaNA_1.01.02_3808", "session_date": "1753-09-24", "date": "1753-09-23", "date_line": "NL-HaNA_1.01.02_3808_0372-line-1342-2733-730-66", "date_scan": "NL-HaNA_1.01.02_3808_0372", "date_string": "Dominica den 23 September"}, {"inventory_num": 3808, "inventory_id": "NL-HaNA_1.01.02_3808", "session_date": "1753-09-24", "date": "1753-09-24", "date_line": "NL-HaNA_1.01.02_3808_0372-line-1387-2926-629-69", "date_scan": "NL-HaNA_1.01.02_3808_0372", "date_string": "Luna den 24 September"}, {"inventory_num": 3808, "inventory_id": "NL-HaNA_1.01.02_3808", "session_date": "1753-09-25", "date": "1753-09-25", "date_line": "NL-HaNA_1.01.02_3808_0373-line-482-2618-658-68", "date_scan": "NL-HaNA_1.01.02_3808_0373", "date_string": "Martis den 25 September"}, {"inventory_num": 3808, "inventory_id": "NL-HaNA_1.01.02_3808", "session_date": "1753-09-26", "date": "1753-09-26", "date_line": "NL-HaNA_1.01.02_3808_0374-line-2462-554-701-61", "date_scan": "NL-HaNA_1.01.02_3808_0374", "date_string": "Mercurii den 26 September"}, {"inventory_num": 3808, "inventory_id": "NL-HaNA_1.01.02_3808", "session_date": "1753-09-27", "date": "1753-09-27", "date_line": "NL-HaNA_1.01.02_3808_0376-line-1439-2633-624-62", "date_scan": "NL-HaNA_1.01.02_3808_0376", "date_string": "Jovis den 27 September"}, {"inventory_num": 3808, "inventory_id": "NL-HaNA_1.01.02_3808", "session_date": "1753-09-28", "date": "1753-09-28", "date_line": "NL-HaNA_1.01.02_3808_0377-line-1406-2331-667-62", "date_scan": "NL-HaNA_1.01.02_3808_0377", "date_string": "Veneris den 28 September"}, {"inventory_num": 3808, "inventory_id": "NL-HaNA_1.01.02_3808", "session_date": "1753-10-01", "date": "1753-09-29", "date_line": "NL-HaNA_1.01.02_3808_0378-line-2447-3182-696-65", "date_scan": "NL-HaNA_1.01.02_3808_0378", "date_string": "Sabbathi den 29 September"}, {"inventory_num": 3808, "inventory_id": "NL-HaNA_1.01.02_3808", "session_date": "1753-10-01", "date": "1753-09-30", "date_line": "NL-HaNA_1.01.02_3808_0378-line-3396-458-725-61", "date_scan": "NL-HaNA_1.01.02_3808_0378", "date_string": "Dominica den 30 September"}, {"inventory_num": 3808, "inventory_id": "NL-HaNA_1.01.02_3808", "session_date": "1753-10-01", "date": "1753-10-01", "date_line": "NL-HaNA_1.01.02_3808_0378-line-3493-651-545-56", "date_scan": "NL-HaNA_1.01.02_3808_0378", "date_string": "Luna den 1 October"}, {"inventory_num": 3808, "inventory_id": "NL-HaNA_1.01.02_3808", "session_date": "1753-10-02", "date": "1753-10-02", "date_line": "NL-HaNA_1.01.02_3808_0381-line-560-2816-564-50", "date_scan": "NL-HaNA_1.01.02_3808_0381", "date_string": "Martis den 2 October"}, {"inventory_num": 3808, "inventory_id": "NL-HaNA_1.01.02_3808", "session_date": "1753-10-03", "date": "1753-10-03", "date_line": "NL-HaNA_1.01.02_3808_0438-line-475-1764-634-72", "date_scan": "NL-HaNA_1.01.02_3808_0438", "date_string": "Mercurii den 3 October"}, {"inventory_num": 3808, "inventory_id": "NL-HaNA_1.01.02_3808", "session_date": "1753-10-04", "date": "1753-10-04", "date_line": "NL-HaNA_1.01.02_3808_0438-line-1452-789-539-60", "date_scan": "NL-HaNA_1.01.02_3808_0438", "date_string": "Jovis den 4 October"}, {"inventory_num": 3808, "inventory_id": "NL-HaNA_1.01.02_3808", "session_date": "1753-10-05", "date": "1753-10-05", "date_line": "NL-HaNA_1.01.02_3808_0439-line-2568-1399-572-54", "date_scan": "NL-HaNA_1.01.02_3808_0439", "date_string": "Veneris den 5 October"}, {"inventory_num": 3808, "inventory_id": "NL-HaNA_1.01.02_3808", "session_date": "1753-10-08", "date": "1753-10-06", "date_line": "NL-HaNA_1.01.02_3808_0440-line-471-3182-613-65", "date_scan": "NL-HaNA_1.01.02_3808_0440", "date_string": "Sabbathi den 6 October"}, {"inventory_num": 3808, "inventory_id": "NL-HaNA_1.01.02_3808", "session_date": "1753-10-08", "date": "1753-10-07", "date_line": "NL-HaNA_1.01.02_3808_0440-line-1402-412-650-51", "date_scan": "NL-HaNA_1.01.02_3808_0440", "date_string": "Dominica den 7 October"}, {"inventory_num": 3808, "inventory_id": "NL-HaNA_1.01.02_3808", "session_date": "1753-10-08", "date": "1753-10-08", "date_line": "NL-HaNA_1.01.02_3808_0440-line-1459-601-548-59", "date_scan": "NL-HaNA_1.01.02_3808_0440", "date_string": "Luna den 8 October"}, {"inventory_num": 3808, "inventory_id": "NL-HaNA_1.01.02_3808", "session_date": "1753-10-09", "date": "1753-10-09", "date_line": "NL-HaNA_1.01.02_3808_0441-line-498-1728-568-57", "date_scan": "NL-HaNA_1.01.02_3808_0441", "date_string": "Martis den 9 October"}, {"inventory_num": 3808, "inventory_id": "NL-HaNA_1.01.02_3808", "session_date": "1753-10-10", "date": "1753-10-10", "date_line": "NL-HaNA_1.01.02_3808_0444-line-2573-1668-667-54", "date_scan": "NL-HaNA_1.01.02_3808_0444", "date_string": "Mercurii den 10 October"}, {"inventory_num": 3808, "inventory_id": "NL-HaNA_1.01.02_3808", "session_date": "1753-10-11", "date": "1753-10-11", "date_line": "NL-HaNA_1.01.02_3808_0446-line-3588-1792-568-59", "date_scan": "NL-HaNA_1.01.02_3808_0446", "date_string": "Jovis den 11 October"}, {"inventory_num": 3808, "inventory_id": "NL-HaNA_1.01.02_3808", "session_date": "1753-10-12", "date": "1753-10-12", "date_line": "NL-HaNA_1.01.02_3808_0447-line-2580-3203-607-59", "date_scan": "NL-HaNA_1.01.02_3808_0447", "date_string": "Veneris den 12 October"}, {"inventory_num": 3808, "inventory_id": "NL-HaNA_1.01.02_3808", "session_date": "1753-10-15", "date": "1753-10-13", "date_line": "NL-HaNA_1.01.02_3808_0449-line-447-2545-640-53", "date_scan": "NL-HaNA_1.01.02_3808_0449", "date_string": "Sabbathi den 13 October"}, {"inventory_num": 3808, "inventory_id": "NL-HaNA_1.01.02_3808", "session_date": "1753-10-15", "date": "1753-10-14", "date_line": "NL-HaNA_1.01.02_3808_0449-line-424-2728-674-57", "date_scan": "NL-HaNA_1.01.02_3808_0449", "date_string": "Dominica den 14 October"}, {"inventory_num": 3808, "inventory_id": "NL-HaNA_1.01.02_3808", "session_date": "1753-10-15", "date": "1753-10-15", "date_line": "NL-HaNA_1.01.02_3808_0449-line-497-2907-574-52", "date_scan": "NL-HaNA_1.01.02_3808_0449", "date_string": "Luna den 15 October"}, {"inventory_num": 3808, "inventory_id": "NL-HaNA_1.01.02_3808", "session_date": "1753-10-16", "date": "1753-10-16", "date_line": "NL-HaNA_1.01.02_3808_0449-line-3527-998-592-60", "date_scan": "NL-HaNA_1.01.02_3808_0449", "date_string": "Martis den 16 October"}, {"inventory_num": 3808, "inventory_id": "NL-HaNA_1.01.02_3808", "session_date": "1753-10-17", "date": "1753-10-17", "date_line": "NL-HaNA_1.01.02_3808_0451-line-451-2151-652-54", "date_scan": "NL-HaNA_1.01.02_3808_0451", "date_string": "Mercurii den 17 October"}, {"inventory_num": 3808, "inventory_id": "NL-HaNA_1.01.02_3808", "session_date": "1753-10-18", "date": "1753-10-18", "date_line": "NL-HaNA_1.01.02_3808_0452-line-1456-3096-560-72", "date_scan": "NL-HaNA_1.01.02_3808_0452", "date_string": "Jovis den 18 October"}, {"inventory_num": 3808, "inventory_id": "NL-HaNA_1.01.02_3808", "session_date": "1753-10-19", "date": "1753-10-19", "date_line": "NL-HaNA_1.01.02_3808_0453-line-494-1954-602-60", "date_scan": "NL-HaNA_1.01.02_3808_0453", "date_string": "Veneris den 19 October"}, {"inventory_num": 3808, "inventory_id": "NL-HaNA_1.01.02_3808", "session_date": "1753-10-22", "date": "1753-10-20", "date_line": "NL-HaNA_1.01.02_3808_0454-line-2557-2893-638-51", "date_scan": "NL-HaNA_1.01.02_3808_0454", "date_string": "Sabbathi den 20 October"}, {"inventory_num": 3808, "inventory_id": "NL-HaNA_1.01.02_3808", "session_date": "1753-10-22", "date": "1753-10-21", "date_line": "NL-HaNA_1.01.02_3808_0454-line-2534-3091-674-48", "date_scan": "NL-HaNA_1.01.02_3808_0454", "date_string": "Dominica den 21 October"}, {"inventory_num": 3808, "inventory_id": "NL-HaNA_1.01.02_3808", "session_date": "1753-10-22", "date": "1753-10-22", "date_line": "NL-HaNA_1.01.02_3808_0454-line-2609-3277-570-49", "date_scan": "NL-HaNA_1.01.02_3808_0454", "date_string": "Luna den 22 October"}, {"inventory_num": 3808, "inventory_id": "NL-HaNA_1.01.02_3808", "session_date": "1753-10-23", "date": "1753-10-23", "date_line": "NL-HaNA_1.01.02_3808_0457-line-495-2742-597-52", "date_scan": "NL-HaNA_1.01.02_3808_0457", "date_string": "Martis den 23 October"}, {"inventory_num": 3808, "inventory_id": "NL-HaNA_1.01.02_3808", "session_date": "1753-10-24", "date": "1753-10-24", "date_line": "NL-HaNA_1.01.02_3808_0458-line-1398-1535-658-59", "date_scan": "NL-HaNA_1.01.02_3808_0458", "date_string": "Mercurii den 24 October"}, {"inventory_num": 3808, "inventory_id": "NL-HaNA_1.01.02_3808", "session_date": "1753-10-25", "date": "1753-10-25", "date_line": "NL-HaNA_1.01.02_3808_0458-line-3538-1798-563-61", "date_scan": "NL-HaNA_1.01.02_3808_0458", "date_string": "Jovis den 25 October"}, {"inventory_num": 3808, "inventory_id": "NL-HaNA_1.01.02_3808", "session_date": "1753-10-26", "date": "1753-10-26", "date_line": "NL-HaNA_1.01.02_3808_0461-line-510-1952-605-49", "date_scan": "NL-HaNA_1.01.02_3808_0461", "date_string": "Veneris den 26 October"}, {"inventory_num": 3808, "inventory_id": "NL-HaNA_1.01.02_3808", "session_date": "1753-10-29", "date": "1753-10-27", "date_line": "NL-HaNA_1.01.02_3808_0462-line-2573-578-639-53", "date_scan": "NL-HaNA_1.01.02_3808_0462", "date_string": "Sabbathi den 27 October"}, {"inventory_num": 3808, "inventory_id": "NL-HaNA_1.01.02_3808", "session_date": "1753-10-29", "date": "1753-10-28", "date_line": "NL-HaNA_1.01.02_3808_0462-line-2554-772-678-49", "date_scan": "NL-HaNA_1.01.02_3808_0462", "date_string": "Dominica den 28 October"}, {"inventory_num": 3808, "inventory_id": "NL-HaNA_1.01.02_3808", "session_date": "1753-10-29", "date": "1753-10-29", "date_line": "NL-HaNA_1.01.02_3808_0462-line-2630-959-577-64", "date_scan": "NL-HaNA_1.01.02_3808_0462", "date_string": "Luna den 29 October"}, {"inventory_num": 3808, "inventory_id": "NL-HaNA_1.01.02_3808", "session_date": "1753-10-30", "date": "1753-10-30", "date_line": "NL-HaNA_1.01.02_3808_0465-line-1449-737-598-53", "date_scan": "NL-HaNA_1.01.02_3808_0465", "date_string": "Martis den 30 October"}, {"inventory_num": 3808, "inventory_id": "NL-HaNA_1.01.02_3808", "session_date": "1753-10-31", "date": "1753-10-31", "date_line": "NL-HaNA_1.01.02_3808_0466-line-1407-1810-654-55", "date_scan": "NL-HaNA_1.01.02_3808_0466", "date_string": "Mercurii den 31 October"}, {"inventory_num": 3808, "inventory_id": "NL-HaNA_1.01.02_3808", "session_date": "1753-11-01", "date": "1753-11-01", "date_line": "NL-HaNA_1.01.02_3808_0467-line-2658-3200-592-64", "date_scan": "NL-HaNA_1.01.02_3808_0467", "date_string": "Jovis den 1 November"}, {"inventory_num": 3808, "inventory_id": "NL-HaNA_1.01.02_3808", "session_date": "1753-11-02", "date": "1753-11-02", "date_line": "NL-HaNA_1.01.02_3808_0467-line-3564-2625-649-53", "date_scan": "NL-HaNA_1.01.02_3808_0467", "date_string": "Veneris den 2 November"}, {"inventory_num": 3808, "inventory_id": "NL-HaNA_1.01.02_3808", "session_date": "1753-11-05", "date": "1753-11-03", "date_line": "NL-HaNA_1.01.02_3808_0469-line-2510-2650-660-52", "date_scan": "NL-HaNA_1.01.02_3808_0469", "date_string": "Sabbathi den 3 November"}, {"inventory_num": 3808, "inventory_id": "NL-HaNA_1.01.02_3808", "session_date": "1753-11-05", "date": "1753-11-04", "date_line": "NL-HaNA_1.01.02_3808_0469-line-2501-2864-702-55", "date_scan": "NL-HaNA_1.01.02_3808_0469", "date_string": "Dominica den 4 November"}, {"inventory_num": 3808, "inventory_id": "NL-HaNA_1.01.02_3808", "session_date": "1753-11-05", "date": "1753-11-05", "date_line": "NL-HaNA_1.01.02_3808_0469-line-2541-3078-608-59", "date_scan": "NL-HaNA_1.01.02_3808_0469", "date_string": "Luna den 5 November"}, {"inventory_num": 3808, "inventory_id": "NL-HaNA_1.01.02_3808", "session_date": "1753-11-06", "date": "1753-11-06", "date_line": "NL-HaNA_1.01.02_3808_0471-line-1404-1203-632-51", "date_scan": "NL-HaNA_1.01.02_3808_0471", "date_string": "Martis den 6 November"}, {"inventory_num": 3808, "inventory_id": "NL-HaNA_1.01.02_3808", "session_date": "1753-11-07", "date": "1753-11-07", "date_line": "NL-HaNA_1.01.02_3808_0472-line-405-1156-699-53", "date_scan": "NL-HaNA_1.01.02_3808_0472", "date_string": "Mercurii den 7 November"}, {"inventory_num": 3808, "inventory_id": "NL-HaNA_1.01.02_3808", "session_date": "1753-11-08", "date": "1753-11-08", "date_line": "NL-HaNA_1.01.02_3808_0473-line-538-2854-600-63", "date_scan": "NL-HaNA_1.01.02_3808_0473", "date_string": "Jovis den 8 November"}, {"inventory_num": 3808, "inventory_id": "NL-HaNA_1.01.02_3808", "session_date": "1753-11-09", "date": "1753-11-09", "date_line": "NL-HaNA_1.01.02_3808_0474-line-2550-2162-648-56", "date_scan": "NL-HaNA_1.01.02_3808_0474", "date_string": "Veneris den 9 November"}, {"inventory_num": 3808, "inventory_id": "NL-HaNA_1.01.02_3808", "session_date": "1753-11-12", "date": "1753-11-10", "date_line": "NL-HaNA_1.01.02_3808_0477-line-2537-1173-688-58", "date_scan": "NL-HaNA_1.01.02_3808_0477", "date_string": "Sabbathi den 10 November"}, {"inventory_num": 3808, "inventory_id": "NL-HaNA_1.01.02_3808", "session_date": "1753-11-12", "date": "1753-11-11", "date_line": "NL-HaNA_1.01.02_3808_0477-line-2510-1388-728-55", "date_scan": "NL-HaNA_1.01.02_3808_0477", "date_string": "Dominica den 11 November"}, {"inventory_num": 3808, "inventory_id": "NL-HaNA_1.01.02_3808", "session_date": "1753-11-12", "date": "1753-11-12", "date_line": "NL-HaNA_1.01.02_3808_0477-line-2566-1588-634-52", "date_scan": "NL-HaNA_1.01.02_3808_0477", "date_string": "Luna den 12 November"}, {"inventory_num": 3808, "inventory_id": "NL-HaNA_1.01.02_3808", "session_date": "1753-11-13", "date": "1753-11-13", "date_line": "NL-HaNA_1.01.02_3808_0478-line-3456-1371-666-56", "date_scan": "NL-HaNA_1.01.02_3808_0478", "date_string": "Martis den 13 November"}, {"inventory_num": 3808, "inventory_id": "NL-HaNA_1.01.02_3808", "session_date": "1753-11-14", "date": "1753-11-14", "date_line": "NL-HaNA_1.01.02_3808_0479-line-461-1144-729-59", "date_scan": "NL-HaNA_1.01.02_3808_0479", "date_string": "Mercurii den 14 November"}, {"inventory_num": 3808, "inventory_id": "NL-HaNA_1.01.02_3808", "session_date": "1753-11-15", "date": "1753-11-15", "date_line": "NL-HaNA_1.01.02_3808_0479-line-3528-519-617-60", "date_scan": "NL-HaNA_1.01.02_3808_0479", "date_string": "Jovis den 15 November"}, {"inventory_num": 3808, "inventory_id": "NL-HaNA_1.01.02_3808", "session_date": "1753-11-16", "date": "1753-11-16", "date_line": "NL-HaNA_1.01.02_3808_0482-line-476-418-671-51", "date_scan": "NL-HaNA_1.01.02_3808_0482", "date_string": "Veneris den 16 November"}, {"inventory_num": 3808, "inventory_id": "NL-HaNA_1.01.02_3808", "session_date": "1753-11-19", "date": "1753-11-17", "date_line": "NL-HaNA_1.01.02_3808_0482-line-3457-2117-687-55", "date_scan": "NL-HaNA_1.01.02_3808_0482", "date_string": "Sabbathi den 17 November"}, {"inventory_num": 3808, "inventory_id": "NL-HaNA_1.01.02_3808", "session_date": "1753-11-19", "date": "1753-11-18", "date_line": "NL-HaNA_1.01.02_3808_0482-line-3430-2309-725-52", "date_scan": "NL-HaNA_1.01.02_3808_0482", "date_string": "Dominica den 18 November"}, {"inventory_num": 3808, "inventory_id": "NL-HaNA_1.01.02_3808", "session_date": "1753-11-19", "date": "1753-11-19", "date_line": "NL-HaNA_1.01.02_3808_0482-line-3486-2505-628-62", "date_scan": "NL-HaNA_1.01.02_3808_0482", "date_string": "Luna den 19 November"}, {"inventory_num": 3808, "inventory_id": "NL-HaNA_1.01.02_3808", "session_date": "1753-11-20", "date": "1753-11-20", "date_line": "NL-HaNA_1.01.02_3808_0483-line-2481-2932-668-49", "date_scan": "NL-HaNA_1.01.02_3808_0483", "date_string": "Martis den 20 November"}, {"inventory_num": 3808, "inventory_id": "NL-HaNA_1.01.02_3808", "session_date": "1753-11-21", "date": "1753-11-21", "date_line": "NL-HaNA_1.01.02_3808_0485-line-1357-1908-724-50", "date_scan": "NL-HaNA_1.01.02_3808_0485", "date_string": "Mercurii den 21 November"}, {"inventory_num": 3808, "inventory_id": "NL-HaNA_1.01.02_3808", "session_date": "1753-11-22", "date": "1753-11-22", "date_line": "NL-HaNA_1.01.02_3808_0486-line-2539-1135-616-60", "date_scan": "NL-HaNA_1.01.02_3808_0486", "date_string": "Jovis den 22 November"}, {"inventory_num": 3808, "inventory_id": "NL-HaNA_1.01.02_3808", "session_date": "1753-11-23", "date": "1753-11-23", "date_line": "NL-HaNA_1.01.02_3808_0486-line-2498-2540-675-55", "date_scan": "NL-HaNA_1.01.02_3808_0486", "date_string": "Veneris den 23 November"}, {"inventory_num": 3808, "inventory_id": "NL-HaNA_1.01.02_3808", "session_date": "1753-11-26", "date": "1753-11-24", "date_line": "NL-HaNA_1.01.02_3808_0488-line-414-1797-692-56", "date_scan": "NL-HaNA_1.01.02_3808_0488", "date_string": "Sabbathi den 24 November"}, {"inventory_num": 3808, "inventory_id": "NL-HaNA_1.01.02_3808", "session_date": "1753-11-26", "date": "1753-11-25", "date_line": "NL-HaNA_1.01.02_3808_0488-line-389-2038-735-54", "date_scan": "NL-HaNA_1.01.02_3808_0488", "date_string": "Dominica den 25 November"}, {"inventory_num": 3808, "inventory_id": "NL-HaNA_1.01.02_3808", "session_date": "1753-11-26", "date": "1753-11-26", "date_line": "NL-HaNA_1.01.02_3808_0488-line-447-2233-635-49", "date_scan": "NL-HaNA_1.01.02_3808_0488", "date_string": "Luna den 26 November"}, {"inventory_num": 3808, "inventory_id": "NL-HaNA_1.01.02_3808", "session_date": "1753-11-27", "date": "1753-11-27", "date_line": "NL-HaNA_1.01.02_3808_0489-line-2495-1606-665-56", "date_scan": "NL-HaNA_1.01.02_3808_0489", "date_string": "Martis den 27 November"}, {"inventory_num": 3808, "inventory_id": "NL-HaNA_1.01.02_3808", "session_date": "1753-11-28", "date": "1753-11-28", "date_line": "NL-HaNA_1.01.02_3808_0490-line-419-594-723-54", "date_scan": "NL-HaNA_1.01.02_3808_0490", "date_string": "Mercurii den 28 November"}, {"inventory_num": 3808, "inventory_id": "NL-HaNA_1.01.02_3808", "session_date": "1753-11-29", "date": "1753-11-29", "date_line": "NL-HaNA_1.01.02_3808_0492-line-1439-1803-630-57", "date_scan": "NL-HaNA_1.01.02_3808_0492", "date_string": "Jovis den 29 November"}, {"inventory_num": 3808, "inventory_id": "NL-HaNA_1.01.02_3808", "session_date": "1753-11-30", "date": "1753-11-30", "date_line": "NL-HaNA_1.01.02_3808_0493-line-1420-844-668-50", "date_scan": "NL-HaNA_1.01.02_3808_0493", "date_string": "Veneris den 30 November"}, {"inventory_num": 3808, "inventory_id": "NL-HaNA_1.01.02_3808", "session_date": "1753-12-03", "date": "1753-12-01", "date_line": "NL-HaNA_1.01.02_3808_0493-line-2538-3202-649-52", "date_scan": "NL-HaNA_1.01.02_3808_0493", "date_string": "Sabbathi den 1 December"}, {"inventory_num": 3808, "inventory_id": "NL-HaNA_1.01.02_3808", "session_date": "1753-12-03", "date": "1753-12-02", "date_line": "NL-HaNA_1.01.02_3808_0493-line-3446-486-690-59", "date_scan": "NL-HaNA_1.01.02_3808_0493", "date_string": "Dominica den 2 December"}, {"inventory_num": 3808, "inventory_id": "NL-HaNA_1.01.02_3808", "session_date": "1753-12-03", "date": "1753-12-03", "date_line": "NL-HaNA_1.01.02_3808_0493-line-3502-680-589-61", "date_scan": "NL-HaNA_1.01.02_3808_0493", "date_string": "Luna den 3 December"}, {"inventory_num": 3808, "inventory_id": "NL-HaNA_1.01.02_3808", "session_date": "1753-12-04", "date": "1753-12-04", "date_line": "NL-HaNA_1.01.02_3808_0495-line-490-2367-624-58", "date_scan": "NL-HaNA_1.01.02_3808_0495", "date_string": "Martis den 4 December"}, {"inventory_num": 3808, "inventory_id": "NL-HaNA_1.01.02_3808", "session_date": "1753-12-05", "date": "1753-12-05", "date_line": "NL-HaNA_1.01.02_3808_0496-line-1400-2076-686-54", "date_scan": "NL-HaNA_1.01.02_3808_0496", "date_string": "Mercurii den 5 December"}, {"inventory_num": 3808, "inventory_id": "NL-HaNA_1.01.02_3808", "session_date": "1753-12-06", "date": "1753-12-06", "date_line": "NL-HaNA_1.01.02_3808_0498-line-3480-2034-584-56", "date_scan": "NL-HaNA_1.01.02_3808_0498", "date_string": "Jovis den 6 December"}, {"inventory_num": 3808, "inventory_id": "NL-HaNA_1.01.02_3808", "session_date": "1753-12-07", "date": "1753-12-07", "date_line": "NL-HaNA_1.01.02_3808_0499-line-1397-575-628-55", "date_scan": "NL-HaNA_1.01.02_3808_0499", "date_string": "Veneris den 7 December"}, {"inventory_num": 3808, "inventory_id": "NL-HaNA_1.01.02_3808", "session_date": "1753-12-10", "date": "1753-12-08", "date_line": "NL-HaNA_1.01.02_3808_0503-line-486-1246-650-51", "date_scan": "NL-HaNA_1.01.02_3808_0503", "date_string": "Sabbathi den 8 December"}, {"inventory_num": 3808, "inventory_id": "NL-HaNA_1.01.02_3808", "session_date": "1753-12-10", "date": "1753-12-09", "date_line": "NL-HaNA_1.01.02_3808_0503-line-461-1436-695-63", "date_scan": "NL-HaNA_1.01.02_3808_0503", "date_string": "Dominica den 9 December"}, {"inventory_num": 3808, "inventory_id": "NL-HaNA_1.01.02_3808", "session_date": "1753-12-10", "date": "1753-12-10", "date_line": "NL-HaNA_1.01.02_3808_0503-line-506-1635-626-57", "date_scan": "NL-HaNA_1.01.02_3808_0503", "date_string": "Luna den 10 December"}, {"inventory_num": 3808, "inventory_id": "NL-HaNA_1.01.02_3808", "session_date": "1753-12-11", "date": "1753-12-11", "date_line": "NL-HaNA_1.01.02_3808_0504-line-1436-2555-646-53", "date_scan": "NL-HaNA_1.01.02_3808_0504", "date_string": "Martis den 11 December"}, {"inventory_num": 3808, "inventory_id": "NL-HaNA_1.01.02_3808", "session_date": "1753-12-12", "date": "1753-12-12", "date_line": "NL-HaNA_1.01.02_3808_0506-line-461-3001-706-63", "date_scan": "NL-HaNA_1.01.02_3808_0506", "date_string": "Mercurii den 12 December"}, {"inventory_num": 3808, "inventory_id": "NL-HaNA_1.01.02_3808", "session_date": "1753-12-13", "date": "1753-12-13", "date_line": "NL-HaNA_1.01.02_3808_0506-line-2525-3267-619-58", "date_scan": "NL-HaNA_1.01.02_3808_0506", "date_string": "Jovis den 13 December"}, {"inventory_num": 3808, "inventory_id": "NL-HaNA_1.01.02_3808", "session_date": "1753-12-14", "date": "1753-12-14", "date_line": "NL-HaNA_1.01.02_3808_0507-line-1382-1903-666-59", "date_scan": "NL-HaNA_1.01.02_3808_0507", "date_string": "Veneris den 14 December"}, {"inventory_num": 3808, "inventory_id": "NL-HaNA_1.01.02_3808", "session_date": "1753-12-17", "date": "1753-12-15", "date_line": "NL-HaNA_1.01.02_3808_0509-line-2495-3080-680-57", "date_scan": "NL-HaNA_1.01.02_3808_0509", "date_string": "Sabbathi den 15 December"}, {"inventory_num": 3808, "inventory_id": "NL-HaNA_1.01.02_3808", "session_date": "1753-12-17", "date": "1753-12-16", "date_line": "NL-HaNA_1.01.02_3808_0509-line-2466-3261-718-51", "date_scan": "NL-HaNA_1.01.02_3808_0509", "date_string": "Dominica den 16 December"}, {"inventory_num": 3808, "inventory_id": "NL-HaNA_1.01.02_3808", "session_date": "1753-12-17", "date": "1753-12-17", "date_line": "NL-HaNA_1.01.02_3808_0509-line-3465-478-626-56", "date_scan": "NL-HaNA_1.01.02_3808_0509", "date_string": "Luna den 17 December"}, {"inventory_num": 3808, "inventory_id": "NL-HaNA_1.01.02_3808", "session_date": "1753-12-18", "date": "1753-12-18", "date_line": "NL-HaNA_1.01.02_3808_0511-line-2498-1385-659-53", "date_scan": "NL-HaNA_1.01.02_3808_0511", "date_string": "Martis den 18 December"}, {"inventory_num": 3808, "inventory_id": "NL-HaNA_1.01.02_3808", "session_date": "1753-12-19", "date": "1753-12-19", "date_line": "NL-HaNA_1.01.02_3808_0511-line-3420-2122-717-65", "date_scan": "NL-HaNA_1.01.02_3808_0511", "date_string": "Mercurii den 19 December"}, {"inventory_num": 3808, "inventory_id": "NL-HaNA_1.01.02_3808", "session_date": "1753-12-20", "date": "1753-12-20", "date_line": "NL-HaNA_1.01.02_3808_0512-line-3472-2103-628-56", "date_scan": "NL-HaNA_1.01.02_3808_0512", "date_string": "Jovis den 20 December"}, {"inventory_num": 3808, "inventory_id": "NL-HaNA_1.01.02_3808", "session_date": "1753-12-21", "date": "1753-12-21", "date_line": "NL-HaNA_1.01.02_3808_0513-line-3437-1973-658-49", "date_scan": "NL-HaNA_1.01.02_3808_0513", "date_string": "Veneris den 21 December"}, {"inventory_num": 3808, "inventory_id": "NL-HaNA_1.01.02_3808", "session_date": "1753-12-24", "date": "1753-12-22", "date_line": "NL-HaNA_1.01.02_3808_0514-line-436-2313-683-59", "date_scan": "NL-HaNA_1.01.02_3808_0514", "date_string": "Sabbathi den 22 December"}, {"inventory_num": 3808, "inventory_id": "NL-HaNA_1.01.02_3808", "session_date": "1753-12-24", "date": "1753-12-23", "date_line": "NL-HaNA_1.01.02_3808_0514-line-405-2497-726-53", "date_scan": "NL-HaNA_1.01.02_3808_0514", "date_string": "Dominica den 23 December"}, {"inventory_num": 3808, "inventory_id": "NL-HaNA_1.01.02_3808", "session_date": "1753-12-24", "date": "1753-12-24", "date_line": "NL-HaNA_1.01.02_3808_0514-line-461-2676-629-58", "date_scan": "NL-HaNA_1.01.02_3808_0514", "date_string": "Luna den 24 December"}, {"inventory_num": 3808, "inventory_id": "NL-HaNA_1.01.02_3808", "session_date": "1753-12-27", "date": "1753-12-25", "date_line": "NL-HaNA_1.01.02_3808_0514-line-3434-2276-656-64", "date_scan": "NL-HaNA_1.01.02_3808_0514", "date_string": "Martis den 25 December"}, {"inventory_num": 3808, "inventory_id": "NL-HaNA_1.01.02_3808", "session_date": "1753-12-27", "date": "1753-12-26", "date_line": "NL-HaNA_1.01.02_3808_0514-line-3416-2539-716-60", "date_scan": "NL-HaNA_1.01.02_3808_0514", "date_string": "Mercurii den 26 December"}, {"inventory_num": 3808, "inventory_id": "NL-HaNA_1.01.02_3808", "session_date": "1753-12-27", "date": "1753-12-27", "date_line": "NL-HaNA_1.01.02_3808_0514-line-3449-2805-625-65", "date_scan": "NL-HaNA_1.01.02_3808_0514", "date_string": "Jovis den 27 December"}]